Workbook

Sheet LEIA-ME
A1: Verificação V1 do Stage C — Corpus B
A2: Gerado 2026-09-17 por stage_c/verification_v1/v1_build.py. Não edita nenhum registo; o que escreveres aqui é lido por v1_apply.py.
A4: O que é V1
A5: Abres a página citada, confirmas que a citação lá está e decides se ela sustenta o valor registado. G1/G2 (existe, página certa) já passaram por script; G3 (sustenta?) é o teu juízo. V1 não confirma ausências: essas precisam de V2 e não estão aqui.
A7: Como trabalhar
A8: 1. Filtra Tier = T1 em MEC, ADP e MODELOS. Faz T1 inteiro antes de T2–T4: é o que o Cap. 3 nomeia. T2 completa o R5 (claim_status), T3 o R6/R8, T4 o R11/R12.
A9: 2. Artigo a artigo: abre pdfs/<artigo>.V1.pdf. A capa lista os itens; cada citação está destacada na cor do tier e etiquetada com o Nº (MEC-001…). Destaques não localizados levam etiqueta vermelha no topo da página.
A10: 3. Só editas as colunas com fundo amarelo claro. Os valores vêm pré-preenchidos com o que o extractor registou: se estão certos, não mexes; se estão errados, escolhes o valor certo na lista. A célula fica laranja quando difere do registado.
A11: 4. 'Citação sustenta?' = S se a frase, lida no seu parágrafo, justifica o valor (depois da tua correção, se houve). N se não justifica nenhum valor possível; explica na Nota.
A12: 5. 'Mantém?' (MEC/ADP) = N quando a ocorrência não devia existir: não é limitação do modelo (é limitação do estudo ou barreira), duplicado, ou outro motivo na Nota.
A13: 6. 'Verificado' = S quando acabaste o item. Só os itens com S contam como V1.
A14: 7. Em Tempos, escreve os minutos por artigo. Os primeiros 3 artigos dão a estimativa real para o resto.
... A29: Cores dos tiers: T1 amarelo · T2 azul · T3 verde · T4 laranja. Célula laranja-salmão = valor alterado por ti.

Sheet Resumo
A1: Resumo da verificação V1 (fórmulas; atualiza sozinho)
A3: Folha | B3: Tier | C3: Itens | D3: Verificados | E3: % verificados | F3: Com valor alterado | G3: Citação não sustenta | H3: Retirados (Mantém? = N…)
A4: MEC | B4: T1 | C4: =COUNTIF(MEC!$B$2:$B$146,"T1") -> 72 | D4: =COUNTIFS(MEC!$B$2:$B$146,"T1",MEC!$R$2:$R$146,"S") -> 0 | E4: =IF(C4=0,"",D4/C4) -> 0 | F4: =SUMPRODUCT((MEC!$B$2:$B$146="T1")*(((MEC!$M$2:$M$146<>MEC!$S$2:$S$146)+(MEC!$N$2:$N$146<>MEC!$T$2:$T$146)+(MEC!$O$2:$O$146<>MEC!$U$2:$U$146))>0)) -> 0 | G4: =COUNTIFS(MEC!$B$2:$B$146,"T1",MEC!$L$2:$L$146,"N") -> 0 | H4: =COUNTIFS(MEC!$B$2:$B$146,"T1",MEC!$P$2:$P$146,"N*") -> 0
A5: MEC | B5: T2 | C5: =COUNTIF(MEC!$B$2:$B$146,"T2") -> 73 | D5: =COUNTIFS(MEC!$B$2:$B$146,"T2",MEC!$R$2:$R$146,"S") -> 0 | E5: =IF(C5=0,"",D5/C5) -> 0 | F5: =SUMPRODUCT((MEC!$B$2:$B$146="T2")*(((MEC!$M$2:$M$146<>MEC!$S$2:$S$146)+(MEC!$N$2:$N$146<>MEC!$T$2:$T$146)+(MEC!$O$2:$O$146<>MEC!$U$2:$U$146))>0)) -> 0 | G5: =COUNTIFS(MEC!$B$2:$B$146,"T2",MEC!$L$2:$L$146,"N") -> 0 | H5: =COUNTIFS(MEC!$B$2:$B$146,"T2",MEC!$P$2:$P$146,"N*") -> 0
A6: ADP | B6: T1 | C6: =COUNTIF(ADP!$B$2:$B$92,"T1") -> 43 | D6: =COUNTIFS(ADP!$B$2:$B$92,"T1",ADP!$T$2:$T$92,"S") -> 0 | E6: =IF(C6=0,"",D6/C6) -> 0 | F6: =SUMPRODUCT((ADP!$B$2:$B$92="T1")*(((ADP!$N$2:$N$92<>ADP!$U$2:$U$92)+(ADP!$O$2:$O$92<>ADP!$V$2:$V$92)+(ADP!$P$2:$P$92<>ADP!$W$2:$W$92)+(ADP!$Q$2:$Q$92<>ADP!$X$2:$X$92))>0)) -> 0 | G6: =COUNTIFS(ADP!$B$2:$B$92,"T1",ADP!$M$2:$M$92,"N") -> 0 | H6: =COUNTIFS(ADP!$B$2:$B$92,"T1",ADP!$R$2:$R$92,"N*") -> 0
A7: ADP | B7: T3 | C7: =COUNTIF(ADP!$B$2:$B$92,"T3") -> 48 | D7: =COUNTIFS(ADP!$B$2:$B$92,"T3",ADP!$T$2:$T$92,"S") -> 0 | E7: =IF(C7=0,"",D7/C7) -> 0 | F7: =SUMPRODUCT((ADP!$B$2:$B$92="T3")*(((ADP!$N$2:$N$92<>ADP!$U$2:$U$92)+(ADP!$O$2:$O$92<>ADP!$V$2:$V$92)+(ADP!$P$2:$P$92<>ADP!$W$2:$W$92)+(ADP!$Q$2:$Q$92<>ADP!$X$2:$X$92))>0)) -> 0 | G7: =COUNTIFS(ADP!$B$2:$B$92,"T3",ADP!$M$2:$M$92,"N") -> 0 | H7: =COUNTIFS(ADP!$B$2:$B$92,"T3",ADP!$R$2:$R$92,"N*") -> 0
A8: MODELOS | B8: T1 | C8: =COUNTIF(MODELOS!$B$2:$B$133,"T1") -> 103 | D8: =COUNTIFS(MODELOS!$B$2:$B$133,"T1",MODELOS!$P$2:$P$133,"S") -> 0 | E8: =IF(C8=0,"",D8/C8) -> 0 | F8: =SUMPRODUCT((MODELOS!$B$2:$B$133="T1")*(((MODELOS!$N$2:$N$133<>MODELOS!$Q$2:$Q$133))>0)) -> 0 | G8: =COUNTIFS(MODELOS!$B$2:$B$133,"T1",MODELOS!$M$2:$M$133,"N") -> 0 | H8: —
A9: MODELOS | B9: T4 | C9: =COUNTIF(MODELOS!$B$2:$B$133,"T4") -> 29 | D9: =COUNTIFS(MODELOS!$B$2:$B$133,"T4",MODELOS!$P$2:$P$133,"S") -> 0 | E9: =IF(C9=0,"",D9/C9) -> 0 | F9: =SUMPRODUCT((MODELOS!$B$2:$B$133="T4")*(((MODELOS!$N$2:$N$133<>MODELOS!$Q$2:$Q$133))>0)) -> 0 | G9: =COUNTIFS(MODELOS!$B$2:$B$133,"T4",MODELOS!$M$2:$M$133,"N") -> 0 | H9: —
A10: Total | C10: =SUM(C4:C9) -> 368 | D10: =SUM(D4:D9) -> 0 | E10: =IF(C10=0,"",D10/C10) -> 0 | F10: =SUM(F4:F9) -> 0 | G10: =SUM(G4:G9) -> 0

Sheet Listas
A1: effect | B1: cause | C1: claim | D1: adaptation | E1: status | F1: framing | G1: C5 data_origin | H1: C5 boundary | I1: C6 regime | J1: C7 statement | K1: C8 OOS status | L1: C13 | M1: yn | N1: keep | O1: done
A2: non-stationarity of the relationship | B2: fouling | C2: general | D2: rolling window | E2: proposed | F2: ISO 50001/50006 explicit | G2: dedicated meter | H2: exact | I2: not stated | J2: stated with numeric bounds | K2: reported | L2: yes | M2: S | N2: S | O2: S
A3: baseline drift or expiry | B3: catalyst deactivation | C3: applied to the case | D3: segmented baseline | E3: implemented | F3: implicit | G3: site meter | H3: allocated by rule | I3: explicitly none in period | J3: stated qualitatively | K3: not reported | L3: partial | M3: N | N3: N — não é limitação do modelo
A4: validity envelope exceeded | B4: feedstock quality or composition change | C4: empirically demonstrated | D4: change-point | E4: evaluated | F4: absent | G4: invoice or utility bill | H4: allocated by estimate | I4: fixed, not mentioned | J4: not stated | K4: not applicable | L4: no | N4: N — duplicado
A5: statistical misspecification | B5: product mix or grade change | D5: additional normalisation variable | G5: process historian tag | H5: mismatch acknowledged | I5: periodic, interval stated | L5: not reported | N5: N — outro (nota)
A6: observability gap — quantity not measured | B6: equipment degradation or ageing | D6: hybrid physical-statistical | G6: calculated from process data | H6: not reported | I6: event-triggered, trigger stated | L6: not applicable
A7: data quality — missing, erroneous or discontinuous data | B7: operating mode or campaign change | D7: online re-estimation | G7: laboratory assay | I7: rolling window
A8: insufficient data length for the model | B8: ambient conditions | D8: outlier exclusion | G8: simulation | I8: online or adaptive
A9: multi-product allocation | B9: plant or process modification | D9: weighted estimation | G9: not reported
A10: baseload or non-productive energy | B10: concurrent improvement programme | D10: normalisation to a reference product
A11: cross-site comparability | B11: other | D11: improved metering
A12: indicator not meaningful as defined | B12: not stated | D12: other
A13: other
A14: not stated

Sheet MEC
A1: Nº | B1: Tier | C1: Artigo | D1: Autor (ano) | E1: Pág. | F1: Pág. corrigida? | G1: ID no registo | H1: Citação | I1: support_class | J1: Other (verbatim) | K1: Localização no PDF | L1: Citação sustenta? | M1: Efeito | N1: Causa | O1: claim_status | P1: Mantém? | Q1: Nota | R1: Verificado | S1: orig_Efeito | T1: orig_Causa | U1: orig_claim_status
A2: MEC-001 | B2: T1 | C2: rayyan-472535351 | D2: Almanza (2025) | E2: 4 | G2: K1 → M1 | H2: The main assumptions adopted for the simulation model have to do with the fact that the cogeneration plant is representative of the energy and environmental performance of the refinery | I2: direct statement | J2: efeito other: model assumes the cogeneration plant is representative of the whole refinery's energy and environmental performance | K2: destacada | M2: other | N2: not stated | O2: applied to the case | S2: other | T2: not stated | U2: applied to the case
A3: MEC-003 | B3: T1 | C3: rayyan-472535351 | D3: Almanza (2025) | E3: 4 | G3: K3 → M1 | H3: natural gas is sampled from all fossil fuels used as energy sources since it is widely used and considered IEU by the refinery | I3: direct statement | J3: efeito other: only natural gas is modelled as a sample representing all fossil fuels used | K3: destacada | M3: other | N3: not stated | O3: applied to the case | S3: other | T3: not stated | U3: applied to the case
A4: MEC-002 | B4: T1 | C4: rayyan-472535351 | D4: Almanza (2025) | E4: 7 | G4: K2 → M1 | H4: Except for boiler CB5, the values returned by the model are lower than the real values. | I4: direct statement | J4: efeito other: model systematically underestimates natural gas consumption relative to real values (except one boiler) | K4: destacada | M4: other | N4: not stated | O4: empirically demonstrated | S4: other | T4: not stated | U4: empirically demonstrated
A5: MEC-004 | B5: T1 | C5: rayyan-472535351 | D5: Almanza (2025) | E5: 11 | G5: K4 → M1 | H5: these conventional indicators are absolute and can give a distorted perception of overall performance, since energy generation increases in greater proportion to the increase in fuel consumption | I5: direct statement | K5: destacada | M5: indicator not meaningful as defined | N5: not stated | O5: applied to the case | S5: indicator not meaningful as defined | T5: not stated | U5: applied to the case
A6: MEC-005 | B6: T1 | C6: rayyan-472535365 | D6: Moghadasi (2025) | E6: 10 | G6: K1 → M1 | H6: Therefore, all data recorded during startup, overhaul, etc., as well as noise points, were removed from the dataset. | I6: direct statement | J6: causa other: outliers, out-of-range data and startup/overhaul periods in the raw DCS dataset | K6: destacada | M6: data quality — missing, erroneous or discontinuous data | N6: other | O6: empirically demonstrated | S6: data quality — missing, erroneous or discontinuous data | T6: other | U6: empirically demonstrated
A7: MEC-006 | B7: T1 | C7: rayyan-472535365 | D7: Moghadasi (2025) | E7: 10 | G7: K2 → M1 | H7: At first, a multicollinearity study was accomplished in the feature selection procedure to avoid target leakage by choosing independent features. | I7: direct statement | K7: destacada | M7: statistical misspecification | N7: not stated | O7: applied to the case | S7: statistical misspecification | T7: not stated | U7: applied to the case
A8: MEC-007 | B8: T2 | C8: rayyan-472535376 | D8: Benmakhlouf (2025) | E8: 6 | G8: K1 → M1 | H8: Steam and water systems are the most complicated in the plant, as they lack the instruments needed for their proper definition. | I8: direct statement | K8: destacada | M8: observability gap — quantity not measured | N8: not stated | O8: applied to the case | S8: observability gap — quantity not measured | T8: not stated | U8: applied to the case
A9: MEC-008 | B9: T2 | C9: rayyan-472535405 | D9: Khalid (2024) | E9: 3 | G9: K1 → paper-level argument | H9: EnPIs can as effectively be identified and calculated as much detailed data is provided by the mills. | I9: direct statement | K9: destacada | M9: observability gap — quantity not measured | N9: not stated | O9: applied to the case | S9: observability gap — quantity not measured | T9: not stated | U9: applied to the case
A10: MEC-009 | B10: T2 | C10: rayyan-472535405 | D10: Khalid (2024) | E10: 6 | G10: K2 → paper-level argument | H10: The precision of the monitoring system and the efficiency of equipment/process/plants can further give detailed and accurate energy intensity. | I10: requires inference | K10: destacada | M10: data quality — missing, erroneous or discontinuous data | N10: not stated | O10: applied to the case | S10: data quality — missing, erroneous or discontinuous data | T10: not stated | U10: applied to the case
A11: MEC-010 | B11: T1 | C11: rayyan-472535480 | D11: Andersson (2021) | E11: 2 | G11: K1 → paper-level argument | H11: As the performance of production processes varies with changing conditions, such as the feedstock quality, the influence of these conditions on the developed EnPIs has to be accounted for in the analysis of the energy performance | I11: direct statement | K11: destacada | M11: non-stationarity of the relationship | N11: feedstock quality or composition change | O11: general | S11: non-stationarity of the relationship | T11: feedstock quality or composition change | U11: general
A12: MEC-011 | B12: T2 | C12: rayyan-472535480 | D12: Andersson (2021) | E12: 4 | G12: K2 → M1 | H12: Since the normal state of a mill will be unique, as it depends on factors such as technology used, chemicals used, type of end-product, raw material, etc., ‘‘the normal state’’ has to be defined individually for each mill. | I12: direct statement | K12: destacada | M12: cross-site comparability | N12: not stated | O12: applied to the case | S12: cross-site comparability | T12: not stated | U12: applied to the case
A13: MEC-014 | B13: T2 | C13: rayyan-472535480 | D13: Andersson (2021) | E13: 5 | G13: K5 → M2 | H13: the explanatory indicator is not tied to the process of which the descriptive indicators are analyzed. | I13: direct statement | K13: destacada | M13: indicator not meaningful as defined | N13: not stated | O13: applied to the case | S13: indicator not meaningful as defined | T13: not stated | U13: applied to the case
A14: MEC-012 | B14: T1 | C14: rayyan-472535480 | D14: Andersson (2021) | E14: 7 | G14: K3 → M1 | H14: This means that the mill defines multiple normal states of operation for every type of pulp quality produced, raw material used, etc. | I14: direct statement | K14: destacada | M14: non-stationarity of the relationship | N14: product mix or grade change | O14: applied to the case | S14: non-stationarity of the relationship | T14: product mix or grade change | U14: applied to the case
A15: MEC-013 | B15: T1 | C15: rayyan-472535480 | D15: Andersson (2021) | E15: 7 | G15: K4 → paper-level argument | H15: it was found that the amount of residual alkali in the black liquor had increased from 5 g/L to 9 g/L. This resulted in the larger demand of lime in the lime kiln. | I15: direct statement | K15: destacada | M15: non-stationarity of the relationship | N15: operating mode or campaign change | O15: empirically demonstrated | S15: non-stationarity of the relationship | T15: operating mode or campaign change | U15: empirically demonstrated
A16: MEC-018 | B16: T1 | C16: rayyan-472535522 | D16: Espinel-Blanco (2020) | E16: 9 | G16: K4 → A1 | H16: the burners and boilers are always operating at the same load regardless of the level of production | I16: direct statement | K16: destacada | M16: baseload or non-productive energy | N16: operating mode or campaign change | O16: empirically demonstrated | S16: baseload or non-productive energy | T16: operating mode or campaign change | U16: empirically demonstrated
A17: MEC-017 | B17: T2 | C17: rayyan-472535522 | D17: Espinel-Blanco (2020) | E17: 11 | G17: K3 → M2 | H17: the consumption of coal presents a diﬀerent behavior to the production, showing that these variations of consumption are not associated with production but are possibly outside the optimal parameters. | I17: direct statement | K17: destacada | M17: non-stationarity of the relationship | N17: not stated | O17: empirically demonstrated | S17: non-stationarity of the relationship | T17: not stated | U17: empirically demonstrated
A18: MEC-015 | B18: T2 | C18: rayyan-472535522 | D18: Espinel-Blanco (2020) | E18: 18 | G18: K1 → M2 | H18: However, in the case of coal, this value was very low. This can be explained by the fact that there is no measurement of the steam that enters the machine. | I18: direct statement | K18: destacada | M18: observability gap — quantity not measured | N18: not stated | O18: empirically demonstrated | S18: observability gap — quantity not measured | T18: not stated | U18: empirically demonstrated
... A40: MEC-039 | B40: T1 | C40: rayyan-472535582 | D40: Morales (2018) | E40: 2 | G40: K1 → paper-level argument | H40: The energy performance of steam boilers, such as the efficiency and the evaporation ratio can decrease along time because of the poor combustion, heat transfer fouling, poor operation, and low maintenance rate. | I40: direct statement | K40: destacada | M40: non-stationarity of the relationship | N40: fouling | O40: general | S40: non-stationarity of the relationship | T40: fouling | U40: general
A41: MEC-040 | B41: T1 | C41: rayyan-472535582 | D41: Morales (2018) | E41: 5 | G41: K2 → M3 | H41: It is important to note that the low efficiency peaks of 22 January, 17 February and 20 February are associated with the random nature of the process and are not the result of variation in the energy management system. | I41: direct statement | J41: efeito other: some low-efficiency index peaks reflect random process variation rather than genuine management/energy variation; causa other: random nature of the process (random operational variation) | K41: destacada | M41: other | N41: other | O41: empirically demonstrated | S41: other | T41: other | U41: empirically demonstrated
A42: MEC-042 | B42: T2 | C42: rayyan-472535585 | D42: Pelser (2018) | E42: 23 | G42: K2 → A1 | H42: The measurement of this risk could be improved by installing more refined meters on different components of the equipment. | I42: direct statement | K42: destacada | M42: observability gap — quantity not measured | N42: not stated | O42: empirically demonstrated | S42: observability gap — quantity not measured | T42: not stated | U42: empirically demonstrated
A43: MEC-041 | B43: T1 | C43: rayyan-472535585 | D43: Pelser (2018) | E43: 25 | G43: K1 → A1 | H43: The “Clinker production” and “Total energy per clinker produced” EnPIs were not evaluated as part of this study, as the plant does not continuously produce clinker. | I43: direct statement | K43: destacada | M43: insufficient data length for the model | N43: operating mode or campaign change | O43: applied to the case | S43: insufficient data length for the model | T43: operating mode or campaign change | U43: applied to the case
A44: MEC-043 | B44: T1 | C44: rayyan-472535625 | D44: Ikeyama (2017) | E44: 5 | G44: K1 → paper-level argument | H44: when a production volume is decreased, energy consumption which does not contribute to the production volume (called as baseload) has effects on the specific energy consumption. | I44: direct statement | J44: causa other: decrease of production volume | K44: destacada | M44: baseload or non-productive energy | N44: other | O44: general | S44: baseload or non-productive energy | T44: other | U44: general
A45: MEC-044 | B45: T1 | C45: rayyan-472535625 | D45: Ikeyama (2017) | E45: 5 | G45: K2 → paper-level argument | H45: If specific energy consumption is identified as EnPI, decreasing production volume might make to cancel out the effect of energy efficiency activities, because the denominator of the specific energy consumption is the production volume. | I45: direct statement | J45: causa other: decrease of production volume | K45: destacada | M45: indicator not meaningful as defined | N45: other | O45: general | S45: indicator not meaningful as defined | T45: other | U45: general
A46: MEC-046 | B46: T1 | C46: rayyan-472535649 | D46: Ochoa (2017) | E46: 3 | G46: K2 → A1 | H46: In order to calculate an equivalent production, it is necessary to determine a value for the energy consumption as the sum of every level of production times its corresponding energy intensity for every different product, as in Eq(2). | I46: direct statement | K46: destacada | M46: multi-product allocation | N46: product mix or grade change | O46: applied to the case | S46: multi-product allocation | T46: product mix or grade change | U46: applied to the case
A47: MEC-045 | B47: T1 | C47: rayyan-472535649 | D47: Ochoa (2017) | E47: 4 | G47: K1 → A1 | H47: the application of limits of control for data of consumption of gas and production so that to exclude data considered atypical | I47: direct statement | K47: destacada | M47: data quality — missing, erroneous or discontinuous data | N47: not stated | O47: empirically demonstrated | S47: data quality — missing, erroneous or discontinuous data | T47: not stated | U47: empirically demonstrated
A48: MEC-047 | B48: T1 | C48: rayyan-472535649 | D48: Ochoa (2017) | E48: 5 | G48: K3 → M4 | H48: several peaks of high efficiency with a random behavior are evidences, by what it indicates that these peaks located in the area of efficiency energy not are result of improvements in the energy management system of the company. | I48: direct statement | K48: destacada | M48: indicator not meaningful as defined | N48: not stated | O48: empirically demonstrated | S48: indicator not meaningful as defined | T48: not stated | U48: empirically demonstrated
A49: MEC-048 | B49: T1 | C49: rayyan-472535680 | D49: Yao (2016) | E49: 7 | G49: K1 → M1 | H49: the energy baseline model is no longer suitable for estimating the current state of EnPI; the model needs to be rebuilt according to the current data. | I49: direct statement | K49: destacada | M49: baseline drift or expiry | N49: not stated | O49: applied to the case | S49: baseline drift or expiry | T49: not stated | U49: applied to the case
A50: MEC-050 | B50: T1 | C50: rayyan-472535680 | D50: Yao (2016) | E50: 7 | G50: K3 → M1 | H50: if the adjusted decision coefficient is greater than the threshold, it is considered that the model fitting is good; otherwise it is considered that the model fitting is poor; the model structure or impact factors need to be reselected. | I50: direct statement | K50: destacada | M50: statistical misspecification | N50: not stated | O50: general | S50: statistical misspecification | T50: not stated | U50: general
A51: MEC-049 | B51: T1 | C51: rayyan-472535680 | D51: Yao (2016) | E51: 8 | G51: K2 → M1 | H51: Since the cracked gas compression unit is working near the set point, it presents linear relationship between EnPI and impact factors | I51: requires inference | K51: destacada | M51: validity envelope exceeded | N51: operating mode or campaign change | O51: applied to the case | S51: validity envelope exceeded | T51: operating mode or campaign change | U51: applied to the case
A52: MEC-053 | B52: T2 | C52: rayyan-472535748 | D52: Tarasovskii (2014) | E52: 3 | G52: K3 → M1 | H52: The actual unit composition of electric power can vary quite broadly (Fig. 2). | I52: requires inference | K52: destacada | M52: indicator not meaningful as defined | N52: not stated | O52: applied to the case | S52: indicator not meaningful as defined | T52: not stated | U52: applied to the case
A53: MEC-051 | B53: T1 | C53: rayyan-472535748 | D53: Tarasovskii (2014) | E53: 4 | G53: K1 → paper-level argument | H53: existing equipment undergoes wear or is operated outside of its design regimes due to a change in production plans, i.e., the energy-efficiency indices decline | I53: direct statement | K53: destacada | M53: baseline drift or expiry | N53: equipment degradation or ageing | O53: general | S53: baseline drift or expiry | T53: equipment degradation or ageing | U53: general
A54: MEC-052 | B54: T1 | C54: rayyan-472535748 | D54: Tarasovskii (2014) | E54: 4 | G54: K2 → paper-level argument | H54: existing equipment undergoes wear or is operated outside of its design regimes due to a change in production plans, i.e., the energy-efficiency indices decline | I54: direct statement | K54: destacada | M54: baseline drift or expiry | N54: operating mode or campaign change | O54: general | S54: baseline drift or expiry | T54: operating mode or campaign change | U54: general
A55: MEC-054 | B55: T2 | C55: rayyan-472535748 | D55: Tarasovskii (2014) | E55: 4 | G55: K4 → paper-level argument | H55: Even programs in the second group, which calculate norms solely on the basis of a one-factor statistical model – the volume of production – are adequate for simple equipment. | I55: requires inference | K55: destacada | M55: statistical misspecification | N55: not stated | O55: general | S55: statistical misspecification | T55: not stated | U55: general
A56: MEC-055 | B56: T2 | C56: rayyan-472535762 | D56: Castrillón-Mendoza (2013) | E56: 4 | G56: K1 → M1 | H56: Siempre y cuando la relación entre las variables analizadas sea adecuada se considera esta ecuación como la Línea de Base Energética [4], [7-8]. | I56: direct statement | K56: destacada | M56: statistical misspecification | N56: not stated | O56: general | S56: statistical misspecification | T56: not stated | U56: general
A57: MEC-056 | B57: T1 | C57: rayyan-472535762 | D57: Castrillón-Mendoza (2013) | E57: 4 | G57: K2 → M1 | H57: Esta línea meta se traza considerando el mismo valor de la pendiente “m” de la línea base, puesto que se supone en el momento que no hay ningún cambio tecnológico sobre los equipos, áreas o procesos sobre los que se realiza el análisis [4], [7]. | I57: direct statement | K57: destacada | M57: non-stationarity of the relationship | N57: plant or process modification | O57: applied to the case | S57: non-stationarity of the relationship | T57: plant or process modification | U57: applied to the case
... A72: MEC-071 | B72: T2 | C72: rayyan-472535797 | D72: Ottermann (2011) | E72: 4 | G72: K1 → A1 | H72: Thus they are not a good indication of the electrical efficiency of a specific mill or kiln. | I72: direct statement | K72: destacada | M72: indicator not meaningful as defined | N72: not stated | O72: applied to the case | S72: indicator not meaningful as defined | T72: not stated | U72: applied to the case
A73: MEC-072 | B73: T2 | C73: rayyan-472536226 | D73: El-Maghraby (2024) | E73: 3 | G73: K1 → A1 | H73: data sets were cleaned and validated by excluding abnormal values that were outside the Safe Operating Envelope (SOE). | I73: requires inference | J73: efeito other: Model built and bounded to the Safe Operating Envelope (SOE) ranges; data outside the SOE were excluded | K73: destacada | M73: validity envelope exceeded | N73: not stated | O73: applied to the case | S73: validity envelope exceeded | T73: not stated | U73: applied to the case
A74: MEC-073 | B74: T2 | C74: rayyan-472536358 | D74: Bassetti (2025) | E74: 10 | G74: K1 → M3 | H74: Therefore, the model cannot be considered very accurate for small productions (< 200 MNm3) despite all the sites analyzed are included inside the upper and lower curves. | I74: direct statement | K74: destacada | M74: validity envelope exceeded | N74: not stated | O74: empirically demonstrated | S74: validity envelope exceeded | T74: not stated | U74: empirically demonstrated
A75: MEC-074 | B75: T2 | C75: rayyan-472536358 | D75: Bassetti (2025) | E75: 10 | G75: K2 → M3 | H75: However, the lower curve presents negative asymptotic behavior, in the very beginning. | I75: direct statement | K75: destacada | M75: statistical misspecification | N75: not stated | O75: empirically demonstrated | S75: statistical misspecification | T75: not stated | U75: empirically demonstrated
A76: MEC-076 | B76: T1 | C76: rayyan-472536358 | D76: Bassetti (2025) | E76: 10 | G76: K4 → M3 | H76: The production of gas is very variable in terms of total production (from 10⋅106 to 1000⋅106 Nm3/year) and composition of products (that is heterogeneous reported on the energy audits). | I76: direct statement | K76: destacada | M76: cross-site comparability | N76: product mix or grade change | O76: applied to the case | S76: cross-site comparability | T76: product mix or grade change | U76: applied to the case
A77: MEC-075 | B77: T1 | C77: rayyan-472536358 | D77: Bassetti (2025) | E77: 11 | G77: K3 → A1 | H77: This result is aligned with literature data (for liquid higher energy consumption [17]) and it is mainly due to the energy consumption of recompression steps after distillation process. | I77: direct statement | K77: destacada | M77: cross-site comparability | N77: product mix or grade change | O77: empirically demonstrated | S77: cross-site comparability | T77: product mix or grade change | U77: empirically demonstrated
A78: MEC-077 | B78: T2 | C78: rayyan-472536358 | D78: Bassetti (2025) | E78: 13 | G78: K5 → M3 | H78: First, the statistics of 2018 present a higher standard deviation on the Real EnPI (52% vs. 38%), but regression model presents a higher correlation (R2=0.873 vs. 0.736) compared to 2022 data. Hence, it is necessary to improve the comparability of data. | I78: direct statement | J78: efeito other: temporal comparability of the model between audit cycles is limited | K78: destacada | M78: other | N78: not stated | O78: applied to the case | S78: other | T78: not stated | U78: applied to the case
A79: MEC-078 | B79: T1 | C79: rayyan-472536379 | D79: Khalid (2024) | E79: 5 | G79: K1 → M1 | H79: nevertheless there are other parameters (such as the temperature, the humidity, the dirtiness of air, the state of the pipelines, the configuration of the network, ...and many other conditions related to the manufacturing process) which heavily affect the energy and volume computation. | I79: direct statement | K79: destacada | M79: observability gap — quantity not measured | N79: ambient conditions | O79: applied to the case | S79: observability gap — quantity not measured | T79: ambient conditions | U79: applied to the case
A80: MEC-079 | B80: T2 | C80: rayyan-472536379 | D80: Khalid (2024) | E80: 6 | G80: K2 → M1 | H80: more improvements are expected by a better fine-tuning: for instance, selecting more locationspecific data, with higher temporal granularity (a week, a month, every change in the batch process, ...) and a more dedicated data gathering on the production itself (sub-process level) are likely to guarantee the setup and use of a robust and rigorous procedure, with higher and higher converging results. | I80: requires inference | J80: efeito other: coarse temporal/spatial data granularity limits the model's predictive robustness and accuracy | K80: destacada | M80: other | N80: not stated | O80: applied to the case | S80: other | T80: not stated | U80: applied to the case
A81: MEC-080 | B81: T1 | C81: rayyan-472536410 | D81: Le-Anh (2023) | E81: 6 | G81: K1 → A1 | H81: Energy consumption of papermaking processes may vary by different pulps and different products and requires normalization. | I81: direct statement | K81: destacada | M81: multi-product allocation | N81: product mix or grade change | O81: applied to the case | S81: multi-product allocation | T81: product mix or grade change | U81: applied to the case
A82: MEC-081 | B82: T1 | C82: rayyan-472536410 | D82: Le-Anh (2023) | E82: 10 | G82: K2 → A1 | H82: As the product quality has not been compared, the lower SEC of group 1 is explained as the simpler process with fewer stages in the stock preparation section, which has been observed during the preliminary audits at the sample factories. | I82: requires inference | K82: destacada | M82: cross-site comparability | N82: product mix or grade change | O82: applied to the case | S82: cross-site comparability | T82: product mix or grade change | U82: applied to the case
A83: MEC-082 | B83: T1 | C83: rayyan-472536410 | D83: Le-Anh (2023) | E83: 11 | G83: K3 → M2 | H83: Therefore, the discrimination in energy consumption of DIP and non-DIP processes among the factories in Vietnam cannot be considered. | I83: direct statement | K83: destacada | M83: multi-product allocation | N83: product mix or grade change | O83: empirically demonstrated | S83: multi-product allocation | T83: product mix or grade change | U83: empirically demonstrated
A84: MEC-083 | B84: T2 | C84: rayyan-472536410 | D84: Le-Anh (2023) | E84: 13 | G84: K4 → M3 | H84: It has been noted that only group 2 of this subsector with 04 sets of data could be used for benchmarking exercise (Table 7). | I84: direct statement | K84: destacada | M84: insufficient data length for the model | N84: not stated | O84: empirically demonstrated | S84: insufficient data length for the model | T84: not stated | U84: empirically demonstrated
A85: MEC-084 | B85: T2 | C85: rayyan-472536428 | D85: Çaǧman (2022) | E85: 3 | G85: K1 → M5 | H85: The relationship between the flow rate and dB data of air leakage is related to different parameters like operational pressure, temperature, environmental conditions, hole/crack geometry, distance/angle be tween the measurement device and the hole, nozzle geometry of the measurement device’s probe. | I85: direct statement | J85: causa other: dependence on operational pressure, temperature, environmental conditions, hole/crack geometry, distance/angle and probe nozzle geometry | K85: destacada | M85: non-stationarity of the relationship | N85: other | O85: applied to the case | S85: non-stationarity of the relationship | T85: other | U85: applied to the case
A86: MEC-085 | B86: T2 | C86: rayyan-472536428 | D86: Çaǧman (2022) | E86: 3 | G86: K2 → paper-level argument | H86: we cannot measure the diameter of the hole in audits because mostly the diameter of the hole is fractional, not smooth for measuring or located at a high level that it cannot be reached. | I86: direct statement | J86: causa other: hole diameter is fractional, unsmooth or physically inaccessible during audits | K86: destacada | M86: observability gap — quantity not measured | N86: other | O86: applied to the case | S86: observability gap — quantity not measured | T86: other | U86: applied to the case
A87: MEC-089 | B87: T2 | C87: rayyan-472536455 | D87: Bruni (2021) | E87: 3 | G87: K4 → paper-level argument | H87: despite several production processes being not linear | I87: direct statement | J87: causa other: non-linear production processes fitted with linear models | K87: destacada | M87: statistical misspecification | N87: other | O87: general | S87: statistical misspecification | T87: other | U87: general
A88: MEC-086 | B88: T2 | C88: rayyan-472536455 | D88: Bruni (2021) | E88: 6 | G88: K1 → paper-level argument | H88: since EnPIs depend on several parameters, such as plant size, operating parameters, energy carriers used, production process, age of machines and equipment, location and environmental conditions, and business conditions, their determination at the NACE level can have some issue. | I88: direct statement | J88: causa other: plant size, operating parameters, energy carriers used, age of machines, location, and business conditions | K88: destacada | M88: cross-site comparability | N88: other | O88: applied to the case | S88: cross-site comparability | T88: other | U88: applied to the case
A89: MEC-087 | B89: T2 | C89: rayyan-472536455 | D89: Bruni (2021) | E89: 6 | G89: K2 → paper-level argument | H89: In some companies, energy consumption may not have a clear link with production, or some companies do not have a physical production (e.g., service companies); | I89: direct statement | K89: destacada | M89: indicator not meaningful as defined | N89: not stated | O89: general | S89: indicator not meaningful as defined | T89: not stated | U89: general
A90: MEC-088 | B90: T2 | C90: rayyan-472536455 | D90: Bruni (2021) | E90: 6 | G90: K3 → paper-level argument | H90: Variables analysed with these models must not directly include economic variables (such as added value, turnover, etc.), which often have no direct relationship with the physical production processes in manufacturing [26]. | I90: direct statement | J90: causa other: economic variables (added value, turnover) with no direct relationship to physical production | K90: destacada | M90: statistical misspecification | N90: other | O90: general | S90: statistical misspecification | T90: other | U90: general
A91: MEC-090 | B91: T2 | C91: rayyan-472536455 | D91: Bruni (2021) | E91: 10 | G91: K5 → paper-level argument | H91: The correlation coefﬁcient can be very sensitive to “outliers” and may indicate association when, in fact, none exists. | I91: direct statement | J91: causa other: outliers / anomalous items | K91: destacada | M91: statistical misspecification | N91: other | O91: general | S91: statistical misspecification | T91: other | U91: general
A92: MEC-091 | B92: T2 | C92: rayyan-472536455 | D92: Bruni (2021) | E92: 10 | G92: K6 → paper-level argument | H92: A low value certainly indicates an insigniﬁcant relationship between consumption and production (often due to the presence of economic factors). | I92: direct statement | J92: causa other: presence of economic factors | K92: destacada | M92: non-stationarity of the relationship | N92: other | O92: general | S92: non-stationarity of the relationship | T92: other | U92: general
A93: MEC-092 | B93: T1 | C93: rayyan-472536455 | D93: Bruni (2021) | E93: 14 | G93: K7 → A1 | H93: one site was dismissed because of non-continuous production | I93: direct statement | K93: destacada | M93: data quality — missing, erroneous or discontinuous data | N93: operating mode or campaign change | O93: empirically demonstrated | S93: data quality — missing, erroneous or discontinuous data | T93: operating mode or campaign change | U93: empirically demonstrated
A94: MEC-095 | B94: T2 | C94: rayyan-472536486 | D94: Scripcariu (2021) | E94: 2 | G94: K3 → M3 | H94: the cement industry end-user’s electricity use is highly influenced by the demand of the construction industry, which is significantly lower in the cold seasons. | I94: requires inference | J94: causa other: seasonal construction-industry demand | K94: destacada | M94: non-stationarity of the relationship | N94: other | O94: applied to the case | S94: non-stationarity of the relationship | T94: other | U94: applied to the case
A95: MEC-093 | B95: T2 | C95: rayyan-472536486 | D95: Scripcariu (2021) | E95: 4 | G95: K1 → M2 | H95: The EI of the company reached a value of 0.48 t.o.e. per thousand EUR because of the extreme drop in the price of the production (from an average price of 2,108 EUR/ton in 2018 to 1,660 EUR/ton in 2020). | I95: direct statement | J95: causa other: extreme drop in the price of the production | K95: destacada | M95: indicator not meaningful as defined | N95: other | O95: empirically demonstrated | S95: indicator not meaningful as defined | T95: other | U95: empirically demonstrated
A96: MEC-094 | B96: T2 | C96: rayyan-472536486 | D96: Scripcariu (2021) | E96: 5 | G96: K2 → M3 | H96: the SA mechanism only applies for electricity use. While the aluminium industry end-user predominantly uses electricity in its technological processes, the cement industry end-user has a much higher share of fossil fuels compared to electricity. | I96: requires inference | J96: causa other: much higher share of fossil fuels compared to electricity; electricity-only indicator does not capture the dominant fossil-fuel energy | K96: destacada | M96: indicator not meaningful as defined | N96: other | O96: applied to the case | S96: indicator not meaningful as defined | T96: other | U96: applied to the case
A97: MEC-097 | B97: T1 | C97: rayyan-472536487 | D97: Luknongbu (2021) | E97: 4 | G97: K2 → M1 | H97: The other factory that produced handmade glass containers has an entirely different energy usage pattern from the other plants. | I97: direct statement | K97: destacada | M97: cross-site comparability | N97: product mix or grade change | O97: empirically demonstrated | S97: cross-site comparability | T97: product mix or grade change | U97: empirically demonstrated
A98: MEC-096 | B98: T2 | C98: rayyan-472536487 | D98: Luknongbu (2021) | E98: 6 | G98: K1 → paper-level argument | H98: However, the amount of energy consumption tends to change over times. BEC and SEC baseline should also be adjusted accordingly. | I98: direct statement | K98: destacada | M98: baseline drift or expiry | N98: not stated | O98: applied to the case | S98: baseline drift or expiry | T98: not stated | U98: applied to the case
A99: MEC-099 | B99: T2 | C99: rayyan-472536501 | D99: Guo (2020) | E99: 7 | G99: K2 → M1 | H99: primarily because energy input comprises fossil and nonfossil energy; however, the model cannot distinguish between the two energy sources. | I99: direct statement | J99: efeito other: EPI model aggregates energy and cannot distinguish fossil from non-fossil energy sources, distorting the efficiency ranking | K99: destacada | M99: other | N99: not stated | O99: applied to the case | S99: other | T99: not stated | U99: applied to the case
A100: MEC-098 | B100: T2 | C100: rayyan-472536501 | D100: Guo (2020) | E100: 9 | G100: K1 → paper-level argument | H100: Figs. 4e6 show that many calculated values of CCR model are close to 1, so it is difﬁcult to rank by radar charts intuitively. | I100: direct statement | J100: efeito other: CCR/DEA efficiency scores cluster near 1, so the model cannot discriminate and rank DMUs | K100: destacada | M100: other | N100: not stated | O100: empirically demonstrated | S100: other | T100: not stated | U100: empirically demonstrated
A101: MEC-100 | B101: T1 | C101: rayyan-472536518 | D101: Maggiore (2020) | E101: 10 | G101: K1 → M1 | H101: this leads to different results when trying to analyse records received from different countries (e.g. savings reported either in final or primary energy, different references for baseline, different ways of evaluating technical life of the installed equipment); | I101: direct statement | K101: destacada | M101: cross-site comparability | N101: not stated | O101: applied to the case | S101: cross-site comparability | T101: not stated | U101: applied to the case
A102: MEC-101 | B102: T1 | C102: rayyan-472536518 | D102: Maggiore (2020) | E102: 10 | G102: K2 → M1 | H102: There are different quality levels of the reported savings: while in some countries sav ings will be measured and periodically reported with strict verification procedures (e.g. in Italy), in others deemed savings are considered enough, so leading to unreliable results and also in the view of 2030 targets achievement; | I102: direct statement | K102: destacada | M102: data quality — missing, erroneous or discontinuous data | N102: not stated | O102: applied to the case | S102: data quality — missing, erroneous or discontinuous data | T102: not stated | U102: applied to the case
A103: MEC-102 | B103: T1 | C103: rayyan-472536532 | D103: Beisheim (2019) | E103: 7 | G103: K1 → paper-level argument | H103: Such models only represent the data that has been used to parameterize them, so extrapolation usually is not possible and their accuracy depends on the density, accuracy and reproducibility of the available data. | I103: direct statement | K103: destacada | M103: validity envelope exceeded | N103: not stated | O103: general | S103: validity envelope exceeded | T103: not stated | U103: general
A104: MEC-104 | B104: T1 | C104: rayyan-472536532 | D104: Beisheim (2019) | E104: 7 | G104: K3 → paper-level argument | H104: Such models only represent the data that has been used to parameterize them, so extrapolation usually is not possible and their accuracy depends on the density, accuracy and reproducibility of the available data. | I104: direct statement | K104: destacada | M104: data quality — missing, erroneous or discontinuous data | N104: not stated | O104: general | S104: data quality — missing, erroneous or discontinuous data | T104: not stated | U104: general
A105: MEC-108 | B105: T1 | C105: rayyan-472536532 | D105: Beisheim (2019) | E105: 7 | G105: K7 → paper-level argument | H105: In many cases, the use of linear regression models is insuﬃcient since the performance curves of the process data clearly indicate nonlinear behavior. | I105: direct statement | K105: não localizada automaticamente | M105: statistical misspecification | N105: not stated | O105: general | S105: statistical misspecification | T105: not stated | U105: general
A106: MEC-105 | B106: T1 | C106: rayyan-472536532 | D106: Beisheim (2019) | E106: 10 | G106: K4 → paper-level argument | H106: Data prior to modiﬁcations may not be suitable for the model identiﬁcation of the current BDP, but contrariwise a signiﬁcant time period is necessary to collect suﬃcient process data to identify a reliable and accurate BDP model. | I106: direct statement | K106: não localizada automaticamente | M106: baseline drift or expiry | N106: plant or process modification | O106: general | S106: baseline drift or expiry | T106: plant or process modification | U106: general
A107: MEC-106 | B107: T1 | C107: rayyan-472536532 | D107: Beisheim (2019) | E107: 10 | G107: K5 → paper-level argument | H107: Data prior to modiﬁcations may not be suitable for the model identiﬁcation of the current BDP, but contrariwise a signiﬁcant time period is necessary to collect suﬃcient process data to identify a reliable and accurate BDP model. | I107: direct statement | K107: não localizada automaticamente | M107: insufficient data length for the model | N107: not stated | O107: general | S107: insufficient data length for the model | T107: not stated | U107: general
A108: MEC-107 | B108: T1 | C108: rayyan-472536532 | D108: Beisheim (2019) | E108: 11 | G108: K6 → paper-level argument | H108: For continuous processes, the analysis is based upon the assumption that the process is stationary, unless storage terms are taken into account in the computation of the indicators. | I108: direct statement | K108: não localizada automaticamente | M108: non-stationarity of the relationship | N108: not stated | O108: general | S108: non-stationarity of the relationship | T108: not stated | U108: general
A109: MEC-103 | B109: T1 | C109: rayyan-472536532 | D109: Beisheim (2019) | E109: 30 | G109: K2 → A1 | H109: Within these bounds the model is applicable for comparison with process data whereas outside the limits the results have to be handled with care due to the lacking extrapolation capabilities of the BDP model. | I109: direct statement | K109: destacada | M109: validity envelope exceeded | N109: not stated | O109: applied to the case | S109: validity envelope exceeded | T109: not stated | U109: applied to the case
A110: MEC-109 | B110: T1 | C110: rayyan-472536551 | D110: Hashim (2019) | E110: 1 | G110: K1 → M1 | H110: Although such tool does not directly measure an actual and reflect an as-is operational data of the companies’ energy performance, it tracks the achievements in the key work processes or the implementation status of an Energy Management Systems (EnMS). | I110: direct statement | J110: efeito other: the indicator does not directly measure actual/as-is energy performance; it is a proxy for EnMS implementation status | K110: destacada | M110: other | N110: not stated | O110: applied to the case | S110: other | T110: not stated | U110: applied to the case
A111: MEC-110 | B111: T1 | C111: rayyan-472536551 | D111: Hashim (2019) | E111: 14 | G111: K2 → M1 | H111: In addition, dedicated computer programming models can be developed if applicable to minimise the subjectivity of the outcome and for document control purposes. | I111: requires inference | J111: efeito other: subjectivity of the self-assessment outcome underlying the indicator score | K111: destacada | M111: other | N111: not stated | O111: applied to the case | S111: other | T111: not stated | U111: applied to the case
A112: MEC-117 | B112: T2 | C112: rayyan-472536606 | D112: Boyd (2017) | E112: 3 | G112: K7 → paper-level argument | H112: there are many challenges with creating efficiency measures based on price indexes, cost, and other value measurements. | I112: direct statement | K112: destacada | M112: indicator not meaningful as defined | N112: not stated | O112: general | S112: indicator not meaningful as defined | T112: not stated | U112: general
A113: MEC-118 | B113: T1 | C113: rayyan-472536606 | D113: Boyd (2017) | E113: 6 | G113: K8 → M1 | H113: the energy use of the plant will depend on the level and mix of products produced. | I113: direct statement | K113: destacada | M113: multi-product allocation | N113: product mix or grade change | O113: general | S113: multi-product allocation | T113: product mix or grade change | U113: general
A114: MEC-112 | B114: T1 | C114: rayyan-472536606 | D114: Boyd (2017) | E114: 7 | G114: K2 → M1 | H114: For cement plants, the hardness and moisture content of the limestone is hypothesized to influence energy use, but no consistent data is available for this, leaving it the subject of future analysis if data can be collected. | I114: direct statement | K114: destacada | M114: observability gap — quantity not measured | N114: feedstock quality or composition change | O114: applied to the case | S114: observability gap — quantity not measured | T114: feedstock quality or composition change | U114: applied to the case
A115: MEC-113 | B115: T2 | C115: rayyan-472536606 | D115: Boyd (2017) | E115: 7 | G115: K3 → M1 | H115: when the HVAC component of energy use is small relative to total plant consumption, the statistical approach may not be able to measure the effect accurately enough to meet tests for reliability. | I115: direct statement | K115: destacada | M115: statistical misspecification | N115: not stated | O115: general | S115: statistical misspecification | T115: not stated | U115: general
A116: MEC-111 | B116: T2 | C116: rayyan-472536606 | D116: Boyd (2017) | E116: 11 | G116: K1 → M1 | H116: These are admittedly strong assumptions. | I116: direct statement | K116: destacada | M116: statistical misspecification | N116: not stated | O116: applied to the case | S116: statistical misspecification | T116: not stated | U116: applied to the case
A117: MEC-116 | B117: T2 | C117: rayyan-472536606 | D117: Boyd (2017) | E117: 13 | G117: K6 → M1 | H117: some data is dropped due to missing variables from incomplete reporting or other data quality screens such as for extreme outliers. | I117: direct statement | K117: destacada | M117: data quality — missing, erroneous or discontinuous data | N117: not stated | O117: applied to the case | S117: data quality — missing, erroneous or discontinuous data | T117: not stated | U117: applied to the case
A118: MEC-114 | B118: T2 | C118: rayyan-472536606 | D118: Boyd (2017) | E118: 15 | G118: K4 → M1 | H118: the study for pulp mills measures the efficiency of net purchased energy and pulp mills provide a large amount of internally generated power from black liquor and CHP. | I118: direct statement | J118: causa other: large internally generated power from black liquor and CHP, so only net purchased energy is measured | K118: destacada | M118: cross-site comparability | N118: other | O118: empirically demonstrated | S118: cross-site comparability | T118: other | U118: empirically demonstrated
A119: MEC-115 | B119: T2 | C119: rayyan-472536606 | D119: Boyd (2017) | E119: 19 | G119: K5 → paper-level argument | H119: recognizing that the variance of simple energy intensity would overstate the range of efficiency. | I119: direct statement | K119: destacada | M119: indicator not meaningful as defined | N119: not stated | O119: applied to the case | S119: indicator not meaningful as defined | T119: not stated | U119: applied to the case
A120: MEC-119 | B120: T2 | C120: rayyan-472536612 | D120: Bonfà (2017) | E120: 2 | G120: K1 → paper-level argument | H120: The already possessed data have been resulted unreliable because of some non-negligible approximations. First of all, it is impossible to know their veracity; in many cases the consumption data come from estimates made on productions of hours or even relying on electric bills. | I120: direct statement | K120: destacada | M120: data quality — missing, erroneous or discontinuous data | N120: not stated | O120: applied to the case | S120: data quality — missing, erroneous or discontinuous data | T120: not stated | U120: applied to the case
A121: MEC-120 | B121: T2 | C121: rayyan-472536612 | D121: Bonfà (2017) | E121: 2 | G121: K2 → paper-level argument | H121: Also, more importantly, it was not possible to use a common standard to develop a reliable benchmark methodology. | I121: direct statement | K121: destacada | M121: cross-site comparability | N121: not stated | O121: applied to the case | S121: cross-site comparability | T121: not stated | U121: applied to the case
A122: MEC-124 | B122: T1 | C122: rayyan-472536612 | D122: Bonfà (2017) | E122: 3 | G122: K6 → M2 | H122: The two KPIs used cannot outline an overview of the situation about the efficiency of the compressed air generation system because of the great difference of the production volumes between the various sectors | I122: direct statement | K122: destacada | M122: indicator not meaningful as defined | N122: product mix or grade change | O122: applied to the case | S122: indicator not meaningful as defined | T122: product mix or grade change | U122: applied to the case
A123: MEC-121 | B123: T1 | C123: rayyan-472536612 | D123: Bonfà (2017) | E123: 4 | G123: K3 → M3 | H123: By comparing the energy consumption in kWhe CAS/m3 it is assumed that the working conditions do not vary significantly between all the enterprises, hence restricting the applications of this approach (Longo et al. (2016)). | I123: direct statement | K123: destacada | M123: validity envelope exceeded | N123: operating mode or campaign change | O123: applied to the case | S123: validity envelope exceeded | T123: operating mode or campaign change | U123: applied to the case
A124: MEC-122 | B124: T2 | C124: rayyan-472536612 | D124: Bonfà (2017) | E124: 4 | G124: K4 → M4 | H124: to have a relation between the electric consumption and the air production it is assumed that it is possible to scale linearly inputs and outputs, i.e. it is assumed constant return to scale. | I124: direct statement | K124: destacada | M124: statistical misspecification | N124: not stated | O124: applied to the case | S124: statistical misspecification | T124: not stated | U124: applied to the case
A125: MEC-123 | B125: T2 | C125: rayyan-472536612 | D125: Bonfà (2017) | E125: 4 | G125: K5 → A1 | H125: If only the measured data have been considered, for some sectors, the regression loses its significance. | I125: direct statement | K125: destacada | M125: statistical misspecification | N125: not stated | O125: empirically demonstrated | S125: statistical misspecification | T125: not stated | U125: empirically demonstrated
A126: MEC-125 | B126: T2 | C126: rayyan-472536612 | D126: Bonfà (2017) | E126: 4 | G126: K7 → A1 | H126: the firms which have not measured the compressed air production might have estimated their data starting from some assumption coming from literature; that kind of data would falsify the analysis. | I126: direct statement | K126: destacada | M126: data quality — missing, erroneous or discontinuous data | N126: not stated | O126: applied to the case | S126: data quality — missing, erroneous or discontinuous data | T126: not stated | U126: applied to the case
A127: MEC-126 | B127: T2 | C127: rayyan-472536612 | D127: Bonfà (2017) | E127: 4 | G127: K8 → A1 | H127: Even if the data are derived from direct measurements not all companies are equipped with the necessary tools and there is not a unique procedure that can determine the power consumption for the compressor park. | I127: direct statement | K127: destacada | M127: observability gap — quantity not measured | N127: not stated | O127: applied to the case | S127: observability gap — quantity not measured | T127: not stated | U127: applied to the case
A128: MEC-130 | B128: T2 | C128: rayyan-472536644 | D128: Boyd (2016) | E128: 4 | G128: K4 → M1 | H128: linear regression estimates of the parameters rely on the proposition that any departures in the plant data from Eq. 1, which cannot be directly observed, are randomly distributed within the population. | I128: direct statement | K128: destacada | M128: statistical misspecification | N128: not stated | O128: applied to the case | S128: statistical misspecification | T128: not stated | U128: applied to the case
A129: MEC-128 | B129: T2 | C129: rayyan-472536644 | D129: Boyd (2016) | E129: 6 | G129: K2 → M1 | H129: for some plants, oxygen was hard to track or record and there were many gaps in the data, especially in the earlier years of the dataset. | I129: direct statement | K129: destacada | M129: data quality — missing, erroneous or discontinuous data | N129: not stated | O129: empirically demonstrated | S129: data quality — missing, erroneous or discontinuous data | T129: not stated | U129: empirically demonstrated
A130: MEC-129 | B130: T2 | C130: rayyan-472536644 | D130: Boyd (2016) | E130: 6 | G130: K3 → M1 | H130: Scrap is not an essential material in steel production although it is commonly used but is sometimes difficult to track in internal production statistics. | I130: direct statement | K130: destacada | M130: data quality — missing, erroneous or discontinuous data | N130: not stated | O130: empirically demonstrated | S130: data quality — missing, erroneous or discontinuous data | T130: not stated | U130: empirically demonstrated
... A132: MEC-127 | B132: T2 | C132: rayyan-472536644 | D132: Boyd (2016) | E132: 14 | G132: K1 → M2 | H132: The analysis clearly demonstrates that energy per ton of steel is an inadequate measure of energy efficiency and that plant specific factors have a large impact on energy use that should not be misconstrued as inefficiency. | I132: direct statement | K132: destacada | M132: indicator not meaningful as defined | N132: not stated | O132: empirically demonstrated | S132: indicator not meaningful as defined | T132: not stated | U132: empirically demonstrated
A133: MEC-132 | B133: T2 | C133: rayyan-472536693 | D133: Sivill (2013) | E133: 9 | G133: K1 → M1 | H133: such as the issue of how to correct the effect of the operation rate on speciﬁc energy consumption. | I133: direct statement | J133: causa other: operation rate | K133: destacada | M133: non-stationarity of the relationship | N133: other | O133: applied to the case | S133: non-stationarity of the relationship | T133: other | U133: applied to the case
A134: MEC-136 | B134: T2 | C134: rayyan-472536693 | D134: Sivill (2013) | E134: 9 | G134: K5 → M1 | H134: External benchmarks, although subject to commensurability issues, were available and used in certain industries. | I134: direct statement | K134: destacada | M134: cross-site comparability | N134: not stated | O134: applied to the case | S134: cross-site comparability | T134: not stated | U134: applied to the case
A135: MEC-137 | B135: T2 | C135: rayyan-472536693 | D135: Sivill (2013) | E135: 9 | F135: sim, era 10 | G135: K6 → paper-level argument | H135: indicators often lose their variance over time. | I135: direct statement | K135: destacada | M135: indicator not meaningful as defined | N135: not stated | O135: general | S135: indicator not meaningful as defined | T135: not stated | U135: general
A136: MEC-138 | B136: T2 | C136: rayyan-472536693 | D136: Sivill (2013) | E136: 9 | G136: K7 → M1 | H136: These indicators are typically not corrected in reporting with respect to any explanatory factors. | I136: direct statement | K136: destacada | M136: indicator not meaningful as defined | N136: not stated | O136: applied to the case | S136: indicator not meaningful as defined | T136: not stated | U136: applied to the case
...

Sheet ADP
A1: Nº | B1: Tier | C1: Artigo | D1: Autor (ano) | E1: Pág. | F1: Pág. corrigida? | G1: ID no registo | H1: Citação | I1: support_class | J1: Other (verbatim) | K1: Mecanismos do artigo | L1: Localização no PDF | M1: Citação sustenta? | N1: Adaptação | O1: Estado | P1: Enquadramento normativo | Q1: Liga a mecanismo (K-id) | R1: Mantém? | S1: Nota | T1: Verificado | U1: orig_Adaptação | V1: orig_Estado | W1: orig_Enquadramento normativo | X1: orig_Liga a mecanismo (K-id)
A2: ADP-001 | B2: T1 | C2: rayyan-472535351 | D2: Almanza (2025) | E2: 7 | G2: D1 → M1 | H2: Emissions of CO2, CO, SO2 and NO per unit of energy generated: It is the proposed relative measure of atmospheric pollutant emissions per unit of energy generated, which most accurately shows the variation in the SEA. | I2: direct statement | K2: K1 (other); K2 (other); K3 (other); K4 (indicator not meaningful as defined) | L2: destacada | N2: additional normalisation variable | O2: proposed | P2: ISO 50001/50006 explicit | Q2: K4 | U2: additional normalisation variable | V2: proposed | W2: ISO 50001/50006 explicit | X2: K4
A3: ADP-003 | B3: T1 | C3: rayyan-472535365 | D3: Moghadasi (2025) | E3: 6 | G3: D2 → A1 | H3: In the clustering part, the whole sample points were divided into the nominal working conditions clusters utilizing the k-means algorithm since the existing data contains similar status subgroups of the EDU's operation. | I3: direct statement | K3: K1 (data quality — missing, erroneous or discontinuous data); K2 (statistical misspecification) | L3: não localizada automaticamente | N3: segmented baseline | O3: implemented | P3: implicit | U3: segmented baseline | V3: implemented | W3: implicit
A4: ADP-002 | B4: T1 | C4: rayyan-472535365 | D4: Moghadasi (2025) | E4: 10 | G4: D1 → M1 | H4: Then, the outliers and out-of-range values were filtered out from the dataset using univariate and multivariate approaches for the remaining components. | I4: direct statement | K4: K1 (data quality — missing, erroneous or discontinuous data); K2 (statistical misspecification) | L4: destacada | N4: outlier exclusion | O4: implemented | P4: implicit | Q4: K1 | U4: outlier exclusion | V4: implemented | W4: implicit | X4: K1
A5: ADP-004 | B5: T1 | C5: rayyan-472535365 | D5: Moghadasi (2025) | E5: 17 | G5: D3 → A1 | H5: As future work, other ML and optimization algorithms can be applied to quantify the energy saving potential instead of comparing the average energy consumption with the lowest energy usage of the operational modes of the unit. | I5: direct statement | J5: adaptation other: apply other ML and optimization algorithms to quantify energy-saving potential instead of comparing average with lowest energy usage | K5: K1 (data quality — missing, erroneous or discontinuous data); K2 (statistical misspecification) | L5: destacada | N5: other | O5: proposed | P5: absent | U5: other | V5: proposed | W5: absent
A6: ADP-005 | B6: T3 | C6: rayyan-472535376 | D6: Benmakhlouf (2025) | E6: 4 | G6: D1 → M1 | H6: Variable outliers during shutdowns were discarded to take into account only regular operation. | I6: direct statement | K6: K1 (observability gap — quantity not measured) | L6: destacada | N6: outlier exclusion | O6: implemented | P6: absent | U6: outlier exclusion | V6: implemented | W6: absent
A7: ADP-006 | B7: T3 | C7: rayyan-472535405 | D7: Khalid (2024) | E7: 6 | G7: D1 → paper-level argument | H7: Further, a potential tool is foreseen in the use of machine learning techniques which can better assess the various EnPIs, by using all the possible data that can link the complex production with its consumption. | I7: direct statement | J7: adaptation other: use of machine learning techniques to better assess the various EnPIs | K7: K1 (observability gap — quantity not measured); K2 (data quality — missing, erroneous or discontinuous data) | L7: destacada | N7: other | O7: proposed | P7: absent | U7: other | V7: proposed | W7: absent
A8: ADP-007 | B8: T1 | C8: rayyan-472535405 | D8: Khalid (2024) | E8: 6 | G8: D2 → paper-level argument | H8: This model i.e. Fig. 5 can be matured with the continuous monitoring and update of data from different case studies. | I8: requires inference | K8: K1 (observability gap — quantity not measured); K2 (data quality — missing, erroneous or discontinuous data) | L8: destacada | N8: online re-estimation | O8: proposed | P8: implicit | U8: online re-estimation | V8: proposed | W8: implicit
A9: ADP-009 | B9: T3 | C9: rayyan-472535480 | D9: Andersson (2021) | E9: 5 | G9: D2 → M2 | H9: At the reference mill a number of explanatory indicators that affect the descriptive indicators of the chemical recovery system (i.e., the EnPIs with purple background color in Fig. 2) have been defined (Fig. 4). | I9: direct statement | K9: K1 (non-stationarity of the relationship); K2 (cross-site comparability); K3 (non-stationarity of the relationship); K4 (non-stationarity of the relationship); K5 (indicator not meaningful as defined) | L9: destacada | N9: additional normalisation variable | O9: implemented | P9: implicit | Q9: K5 | U9: additional normalisation variable | V9: implemented | W9: implicit | X9: K5
A10: ADP-008 | B10: T3 | C10: rayyan-472535480 | D10: Andersson (2021) | E10: 7 | G10: D1 → M1 | H10: This means that the mill defines multiple normal states of operation for every type of pulp quality produced, raw material used, etc. | I10: direct statement | K10: K1 (non-stationarity of the relationship); K2 (cross-site comparability); K3 (non-stationarity of the relationship); K4 (non-stationarity of the relationship); K5 (indicator not meaningful as defined) | L10: destacada | N10: segmented baseline | O10: proposed | P10: implicit | Q10: K3 | U10: segmented baseline | V10: proposed | W10: implicit | X10: K3
A11: ADP-010 | B11: T1 | C11: rayyan-472535480 | D11: Andersson (2021) | E11: 7 | G11: D3 → M1 | H11: Preferably, it should be on an hourly basis, as changes in production are sometimes short (i.e. daily energy data will sometimes not be sufficient). | I11: direct statement | K11: K1 (non-stationarity of the relationship); K2 (cross-site comparability); K3 (non-stationarity of the relationship); K4 (non-stationarity of the relationship); K5 (indicator not meaningful as defined) | L11: destacada | N11: improved metering | O11: proposed | P11: absent | U11: improved metering | V11: proposed | W11: absent
A12: ADP-011 | B12: T1 | C12: rayyan-472535524 | D12: Beisheim (2020) | E12: 1 | G12: D1 → M1 | H12: an aggregation method is proposed to exploit the analysis of the factors on lower hierarchical layers for the evaluation of the performance of an aggregated domain. | I12: direct statement | J12: adaptation other: hierarchical bottom-up aggregation of process-level energy performance indicators and baselines to site/company level | K12: K1 (cross-site comparability); K2 (multi-product allocation); K3 (observability gap — quantity not measured); K4 (non-stationarity of the relationship); K5 (non-stationarity of the relationship); K6 (multi-product allocation) | L12: destacada | N12: other | O12: implemented | P12: ISO 50001/50006 explicit | U12: other | V12: implemented | W12: ISO 50001/50006 explicit
A13: ADP-013 | B13: T1 | C13: rayyan-472535524 | D13: Beisheim (2020) | E13: 10 | G13: D3 → M1 | H13: The concept is compatible with the usage of different types of baseline models, e.g. linear regression or artificial neural networks, in one system | I13: direct statement | J13: adaptation other: use of different baseline model types (linear regression or artificial neural networks) within one aggregation system | K13: K1 (cross-site comparability); K2 (multi-product allocation); K3 (observability gap — quantity not measured); K4 (non-stationarity of the relationship); K5 (non-stationarity of the relationship); K6 (multi-product allocation) | L13: destacada | N13: other | O13: implemented | P13: implicit | U13: other | V13: implemented | W13: implicit
A14: ADP-012 | B14: T1 | C14: rayyan-472535524 | D14: Beisheim (2020) | E14: 11 | G14: D2 → M1 | H14: splitting the performance of the plants and of the site into contributions of influenceable and non-influenceable factors. | I14: direct statement | K14: K1 (cross-site comparability); K2 (multi-product allocation); K3 (observability gap — quantity not measured); K4 (non-stationarity of the relationship); K5 (non-stationarity of the relationship); K6 (multi-product allocation) | L14: destacada | N14: additional normalisation variable | O14: implemented | P14: ISO 50001/50006 explicit | Q14: K5 | U14: additional normalisation variable | V14: implemented | W14: ISO 50001/50006 explicit | X14: K5
A15: ADP-014 | B15: T3 | C15: rayyan-472535532 | D15: Mahesthi (2020) | E15: 10 | G15: D1 → M6 | H15: Baseline determination by using single regression will be updated using other influential variables so that the use of multiple regression for new baselines will be considered. | I15: direct statement | K15: K1 (non-stationarity of the relationship); K2 (baseload or non-productive energy); K3 (baseload or non-productive energy); K4 (indicator not meaningful as defined) | L15: destacada | N15: additional normalisation variable | O15: proposed | P15: implicit | Q15: K1 | U15: additional normalisation variable | V15: proposed | W15: implicit | X15: K1
A16: ADP-017 | B16: T1 | C16: rayyan-472535550 | D16: Hamedi (2019) | E16: 1 | G16: D3 → A1 | H16: when the relative errors are taken into account, performance of ANN models appears fairly superior compared to the MLR model. | I16: direct statement | J16: adaptation other: comparison of ANN against MLR as alternative baseline models | K16: K1 (indicator not meaningful as defined); K2 (baseload or non-productive energy); K3 (statistical misspecification); K4 (statistical misspecification); K5 (observability gap — quantity not measured); K6 (observability gap — quantity not measured); K7 (data quality — missing, erroneous or discontinuous data); K8 (data quality — missing, erroneous or discontinuous data); K9 (statistical misspecification); K10 (non-stationarity of the relationship) | L16: destacada | N16: other | O16: evaluated | P16: absent | U16: other | V16: evaluated | W16: absent
A17: ADP-015 | B17: T1 | C17: rayyan-472535550 | D17: Hamedi (2019) | E17: 8 | G17: D1 → A1 | H17: after brainstorm with the LDPE engineers (EnPI Tool Instruction Guide, 2011), 8 factors were selected as independent variables (inputs) | I17: direct statement | K17: K1 (indicator not meaningful as defined); K2 (baseload or non-productive energy); K3 (statistical misspecification); K4 (statistical misspecification); K5 (observability gap — quantity not measured); K6 (observability gap — quantity not measured); K7 (data quality — missing, erroneous or discontinuous data); K8 (data quality — missing, erroneous or discontinuous data); K9 (statistical misspecification); K10 (non-stationarity of the relationship) | L17: destacada | N17: additional normalisation variable | O17: implemented | P17: implicit | U17: additional normalisation variable | V17: implemented | W17: implicit
A18: ADP-016 | B18: T1 | C18: rayyan-472535550 | D18: Hamedi (2019) | E18: 8 | G18: D2 → A1 | H18: The noisy data that belong to the days within which, the plant has been under maintenance or long-term overhaul are eliminated to decrease the errors (118 days). | I18: direct statement | K18: K1 (indicator not meaningful as defined); K2 (baseload or non-productive energy); K3 (statistical misspecification); K4 (statistical misspecification); K5 (observability gap — quantity not measured); K6 (observability gap — quantity not measured); K7 (data quality — missing, erroneous or discontinuous data); K8 (data quality — missing, erroneous or discontinuous data); K9 (statistical misspecification); K10 (non-stationarity of the relationship) | L18: destacada | N18: outlier exclusion | O18: implemented | P18: absent | Q18: K8 | U18: outlier exclusion | V18: implemented | W18: absent | X18: K8
A19: ADP-018 | B19: T1 | C19: rayyan-472535550 | D19: Hamedi (2019) | E19: 13 | G19: D4 → A1 | H19: the PCDA cycle (Plan-Do-Check-Act) should be repeated to ﬁnd the best performance and continuously upgrade the baseline. | I19: direct statement | K19: K1 (indicator not meaningful as defined); K2 (baseload or non-productive energy); K3 (statistical misspecification); K4 (statistical misspecification); K5 (observability gap — quantity not measured); K6 (observability gap — quantity not measured); K7 (data quality — missing, erroneous or discontinuous data); K8 (data quality — missing, erroneous or discontinuous data); K9 (statistical misspecification); K10 (non-stationarity of the relationship) | L19: destacada | N19: online re-estimation | O19: proposed | P19: implicit | U19: online re-estimation | V19: proposed | W19: implicit
A20: ADP-019 | B20: T1 | C20: rayyan-472535550 | D20: Hamedi (2019) | E20: 14 | G20: D5 → A1 | H20: the model could also become completed applying more advanced ANNs such as recurrent neural networks. | I20: direct statement | J20: adaptation other: more advanced ANNs such as recurrent neural networks | K20: K1 (indicator not meaningful as defined); K2 (baseload or non-productive energy); K3 (statistical misspecification); K4 (statistical misspecification); K5 (observability gap — quantity not measured); K6 (observability gap — quantity not measured); K7 (data quality — missing, erroneous or discontinuous data); K8 (data quality — missing, erroneous or discontinuous data); K9 (statistical misspecification); K10 (non-stationarity of the relationship) | L20: destacada | N20: other | O20: proposed | P20: absent | U20: other | V20: proposed | W20: absent
A21: ADP-020 | B21: T1 | C21: rayyan-472535582 | D21: Morales (2018) | E21: 5 | G21: D1 → M1 | H21: filtering of data was carried out in order to establish a more stable correlation; with the purpose of not losing functionality between production and energy when it comes to energy indicators analysis, selecting as final criteria 2 standard deviation. | I21: direct statement | K21: K1 (non-stationarity of the relationship); K2 (other) | L21: destacada | N21: outlier exclusion | O21: implemented | P21: implicit | U21: outlier exclusion | V21: implemented | W21: implicit
A22: ADP-023 | B22: T3 | C22: rayyan-472535585 | D22: Pelser (2018) | E22: 13 | G22: D3 → A1 | H22: Developing an effective budgeting system (step 7) ensures that the targets and budgets are adapted according to performance, resulting in continuous improvement and a target that is realistic, but still aims to reach the optimal performance. | I22: requires inference | K22: K1 (insufficient data length for the model); K2 (observability gap — quantity not measured) | L22: destacada | N22: rolling window | O22: implemented | P22: implicit | U22: rolling window | V22: implemented | W22: implicit
A23: ADP-021 | B23: T3 | C23: rayyan-472535585 | D23: Pelser (2018) | E23: 22 | G23: D1 → A1 | H23: tariff structures during the summer and winter months, the trend lines were generated separately for the two cases in the graphs. | I23: direct statement | K23: K1 (insufficient data length for the model); K2 (observability gap — quantity not measured) | L23: destacada | N23: segmented baseline | O23: implemented | P23: absent | U23: segmented baseline | V23: implemented | W23: absent
A24: ADP-022 | B24: T1 | C24: rayyan-472535585 | D24: Pelser (2018) | E24: 23 | G24: D2 → A1 | H24: The measurement of this risk could be improved by installing more refined meters on different components of the equipment. | I24: direct statement | K24: K1 (insufficient data length for the model); K2 (observability gap — quantity not measured) | L24: destacada | N24: improved metering | O24: proposed | P24: absent | Q24: K2 | U24: improved metering | V24: proposed | W24: absent | X24: K2
A25: ADP-024 | B25: T1 | C25: rayyan-472535585 | D25: Pelser (2018) | E25: 27 | G25: D4 → A1 | H25: To adapt this strategy the critical meters required to continuously monitor coal consumption have to be installed. | I25: direct statement | K25: K1 (insufficient data length for the model); K2 (observability gap — quantity not measured) | L25: destacada | N25: improved metering | O25: proposed | P25: absent | U25: improved metering | V25: proposed | W25: absent
A26: ADP-025 | B26: T1 | C26: rayyan-472535625 | D26: Ikeyama (2017) | E26: 5 | G26: D1 → M1 | H26: this function creates calculation models which are fitted to them and manages finely with setting the detail targets. | I26: requires inference | K26: K1 (baseload or non-productive energy); K2 (indicator not meaningful as defined) | L26: destacada | N26: online re-estimation | O26: implemented | P26: implicit | U26: online re-estimation | V26: implemented | W26: implicit
A27: ADP-026 | B27: T1 | C27: rayyan-472535625 | D27: Ikeyama (2017) | E27: 5 | G27: D2 → paper-level argument | H27: JEITA has been suggesting the indicators which can be shown | I27: requires inference | J27: adaptation other: indicators shown as 'result of efforts' (based on ISO 50006), replacing plain specific energy consumption | K27: K1 (baseload or non-productive energy); K2 (indicator not meaningful as defined) | L27: destacada | N27: other | O27: proposed | P27: ISO 50001/50006 explicit | Q27: K1 | U27: other | V27: proposed | W27: ISO 50001/50006 explicit | X27: K1
A28: ADP-028 | B28: T1 | C28: rayyan-472535649 | D28: Ochoa (2017) | E28: 3 | G28: D2 → A1 | H28: The energy relationship of the products αj, corresponds to the number of units of product base that can be elaborated with the energy used to produce a unit of product (j). | I28: direct statement | K28: K1 (data quality — missing, erroneous or discontinuous data); K2 (multi-product allocation); K3 (indicator not meaningful as defined) | L28: destacada | N28: normalisation to a reference product | O28: implemented | P28: implicit | Q28: K2 | U28: normalisation to a reference product | V28: implemented | W28: implicit | X28: K2
A29: ADP-027 | B29: T1 | C29: rayyan-472535649 | D29: Ochoa (2017) | E29: 4 | G29: D1 → A1 | H29: these data considered as outliers will not be considered for the productive plant energy analysis | I29: direct statement | K29: K1 (data quality — missing, erroneous or discontinuous data); K2 (multi-product allocation); K3 (indicator not meaningful as defined) | L29: destacada | N29: outlier exclusion | O29: implemented | P29: implicit | Q29: K1 | U29: outlier exclusion | V29: implemented | W29: implicit | X29: K1
A30: ADP-029 | B30: T1 | C30: rayyan-472535649 | D30: Ochoa (2017) | E30: 5 | G30: D3 → A1 | H30: it is necessary to develop a Software for tracking, measurement, and analysis of the energy performance for each significant use of energy installed and set in operation | I30: direct statement | J30: adaptation other: Software for tracking, measurement, and analysis of the energy performance | K30: K1 (data quality — missing, erroneous or discontinuous data); K2 (multi-product allocation); K3 (indicator not meaningful as defined) | L30: destacada | N30: other | O30: proposed | P30: implicit | U30: other | V30: proposed | W30: implicit
A31: ADP-031 | B31: T1 | C31: rayyan-472535680 | D31: Yao (2016) | E31: 4 | G31: D2 → M1 | H31: Therefore, general function forms are proposed to approximate various nonlinear relationships. The EnPIs are the sum of nonlinear relationships of each impact factor, as shown in the following: | I31: direct statement | J31: adaptation other: B-spline approximation model where each EnPI is expressed as a sum of nonlinear functions of each impact factor, each approximated by a T-order B-spline function, for strongly nonlinear processes | K31: K1 (baseline drift or expiry); K2 (validity envelope exceeded); K3 (statistical misspecification) | L31: destacada | N31: other | O31: proposed | P31: implicit | U31: other | V31: proposed | W31: implicit
A32: ADP-030 | B32: T1 | C32: rayyan-472535680 | D32: Yao (2016) | E32: 7 | G32: D1 → M1 | H32: the model needs to be rebuilt according to the current data. | I32: direct statement | K32: K1 (baseline drift or expiry); K2 (validity envelope exceeded); K3 (statistical misspecification) | L32: destacada | N32: online re-estimation | O32: proposed | P32: ISO 50001/50006 explicit | Q32: K1 | U32: online re-estimation | V32: proposed | W32: ISO 50001/50006 explicit | X32: K1
A33: ADP-032 | B33: T3 | C33: rayyan-472535748 | D33: Tarasovskii (2014) | E33: 4 | G33: D1 → M2 | H33: More complex statistical models are constructed with allowance for several influencing factors. | I33: direct statement | K33: K1 (baseline drift or expiry); K2 (baseline drift or expiry); K3 (indicator not meaningful as defined); K4 (statistical misspecification) | L33: destacada | N33: additional normalisation variable | O33: implemented | P33: implicit | Q33: K4 | U33: additional normalisation variable | V33: implemented | W33: implicit | X33: K4
A34: ADP-034 | B34: T3 | C34: rayyan-472535748 | D34: Tarasovskii (2014) | E34: 4 | G34: D3 → M3 | H34: The errors are even smaller for multi-factorial models, including those which make use of the theory of artificial neural networks or various physical models of equipment constructed on the basis of the results of tests or numerical modeling [4, 5]. | I34: direct statement | K34: K1 (baseline drift or expiry); K2 (baseline drift or expiry); K3 (indicator not meaningful as defined); K4 (statistical misspecification) | L34: destacada | N34: hybrid physical-statistical | O34: implemented | P34: implicit | Q34: K4 | U34: hybrid physical-statistical | V34: implemented | W34: implicit | X34: K4
A35: ADP-033 | B35: T1 | C35: rayyan-472535748 | D35: Tarasovskii (2014) | E35: 6 | G35: D2 → M3 | H35: runs models periodically based on a time period chosen by the user, chooses the best-performing model, and recalculates the existing norms | I35: direct statement | K35: K1 (baseline drift or expiry); K2 (baseline drift or expiry); K3 (indicator not meaningful as defined); K4 (statistical misspecification) | L35: destacada | N35: online re-estimation | O35: implemented | P35: implicit | Q35: K1 | U35: online re-estimation | V35: implemented | W35: implicit | X35: K1
A36: ADP-035 | B36: T3 | C36: rayyan-472535762 | D36: Castrillón-Mendoza (2013) | E36: 7 | G36: D1 → M3 | H36: la tecnología SGIE recomienda establecer una estructura de indicadores de desempeño energético a nivel de empresa o proceso en forma de “árbol de indicadores”, figura 7, de manera tal, que el indicador de eficiencia base 100 de la empresa sea estructurado a partir de los indicadores de eficiencia base 100 de cada uno de las áreas y equipos de uso final que lo componen. | I36: direct statement | K36: K1 (statistical misspecification); K2 (non-stationarity of the relationship); K3 (indicator not meaningful as defined) | L36: destacada | N36: segmented baseline | O36: proposed | P36: implicit | U36: segmented baseline | V36: proposed | W36: implicit
A37: ADP-036 | B37: T3 | C37: rayyan-472535762 | D37: Castrillón-Mendoza (2013) | E37: 7 | G37: D2 → A1 | H37: Como resultado se identificaron siete variables con el mayor impacto en el consumo de energía en los centros de costos críticos de clinkerización, molienda de cemento y primaria, las cuales se resumen en la tabla 3. | I37: direct statement | J37: adaptation other: identificación y estabilización de variables de control operacional por centro de costo de energía | K37: K1 (statistical misspecification); K2 (non-stationarity of the relationship); K3 (indicator not meaningful as defined) | L37: destacada | N37: other | O37: implemented | P37: implicit | U37: other | V37: implemented | W37: implicit
A38: ADP-037 | B38: T1 | C38: rayyan-472535787 | D38: González (2012) | E38: 10 | G38: D1 → M1 | H38: analysis of the causes of deviations, reporting of results, and finally, the modification of target lines. | I38: direct statement | K38: K1 (non-stationarity of the relationship); K2 (baseload or non-productive energy) | L38: destacada | N38: online re-estimation | O38: implemented | P38: implicit | U38: online re-estimation | V38: implemented | W38: implicit
A39: ADP-039 | B39: T3 | C39: rayyan-472535794 | D39: Giacone (2012) | E39: 2 | G39: D2 → paper-level argument | H39: The authors have recently made a contribution to this ﬁeld [21,22], by suggesting the use of the tabular CUSUM control chart. | I39: direct statement | J39: adaptation other: tabular CUSUM control chart to ensure the model refers to the most recent and stable period | K39: K1 (indicator not meaningful as defined); K2 (indicator not meaningful as defined); K3 (cross-site comparability); K4 (cross-site comparability); K5 (cross-site comparability); K6 (indicator not meaningful as defined); K7 (statistical misspecification); K8 (non-stationarity of the relationship); K9 (baseline drift or expiry); K10 (indicator not meaningful as defined); K11 (multi-product allocation) | L39: destacada | N39: other | O39: proposed | P39: absent | U39: other | V39: proposed | W39: absent
A40: ADP-040 | B40: T3 | C40: rayyan-472535794 | D40: Giacone (2012) | E40: 10 | G40: D3 → A2 | H40: it should be complemented with another indicator e for example, the variable consumption ratio k or the marginal consumption c1 e since, in general, SEC depends on the production rate. | I40: direct statement | J40: adaptation other: complement SEC with the variable consumption ratio k or the marginal consumption c1 to separate the production-rate effect | K40: K1 (indicator not meaningful as defined); K2 (indicator not meaningful as defined); K3 (cross-site comparability); K4 (cross-site comparability); K5 (cross-site comparability); K6 (indicator not meaningful as defined); K7 (statistical misspecification); K8 (non-stationarity of the relationship); K9 (baseline drift or expiry); K10 (indicator not meaningful as defined); K11 (multi-product allocation) | L40: destacada | N40: other | O40: implemented | P40: implicit | Q40: K1 | U40: other | V40: implemented | W40: implicit | X40: K1
A41: ADP-041 | B41: T3 | C41: rayyan-472535794 | D41: Giacone (2012) | E41: 10 | G41: D4 → paper-level argument | H41: the comparison of technologies should be performed at full capacity, i.e. at nominal variable consumption ratio kn, which changes from installation to installation. | I41: direct statement | J41: adaptation other: compare technologies at full capacity (nominal variable consumption ratio) to remove the effect of production level | K41: K1 (indicator not meaningful as defined); K2 (indicator not meaningful as defined); K3 (cross-site comparability); K4 (cross-site comparability); K5 (cross-site comparability); K6 (indicator not meaningful as defined); K7 (statistical misspecification); K8 (non-stationarity of the relationship); K9 (baseline drift or expiry); K10 (indicator not meaningful as defined); K11 (multi-product allocation) | L41: destacada | N41: other | O41: proposed | P41: absent | Q41: K3 | U41: other | V41: proposed | W41: absent | X41: K3
A42: ADP-042 | B42: T3 | C42: rayyan-472535794 | D42: Giacone (2012) | E42: 11 | G42: D5 → M4 | H42: This aspect can be addressed through an energy characterisation of the furnace, using daily data instead of monthly data. | I42: direct statement | J42: adaptation other: energy characterisation of the furnace using daily data instead of monthly data to capture the nonlinear behaviour | K42: K1 (indicator not meaningful as defined); K2 (indicator not meaningful as defined); K3 (cross-site comparability); K4 (cross-site comparability); K5 (cross-site comparability); K6 (indicator not meaningful as defined); K7 (statistical misspecification); K8 (non-stationarity of the relationship); K9 (baseline drift or expiry); K10 (indicator not meaningful as defined); K11 (multi-product allocation) | L42: destacada | N42: other | O42: implemented | P42: absent | Q42: K8 | U42: other | V42: implemented | W42: absent | X42: K8
A43: ADP-038 | B43: T3 | C43: rayyan-472535794 | D43: Giacone (2012) | E43: 12 | G43: D1 → A2 | H43: In general, with multiple energy drivers, the multivariate regression analysis can provide a mathematical model of the process energy consumption | I43: direct statement | K43: K1 (indicator not meaningful as defined); K2 (indicator not meaningful as defined); K3 (cross-site comparability); K4 (cross-site comparability); K5 (cross-site comparability); K6 (indicator not meaningful as defined); K7 (statistical misspecification); K8 (non-stationarity of the relationship); K9 (baseline drift or expiry); K10 (indicator not meaningful as defined); K11 (multi-product allocation) | L43: destacada | N43: additional normalisation variable | O43: proposed | P43: absent | U43: additional normalisation variable | V43: proposed | W43: absent
A44: ADP-043 | B44: T3 | C44: rayyan-472535794 | D44: Giacone (2012) | E44: 12 | G44: D6 → paper-level argument | H44: provided that the allocation of the energy consumptions is stipulated among the products, for example in accordance with the steps outlined in LCA standard ISO 14044:2006. | I44: direct statement | K44: K1 (indicator not meaningful as defined); K2 (indicator not meaningful as defined); K3 (cross-site comparability); K4 (cross-site comparability); K5 (cross-site comparability); K6 (indicator not meaningful as defined); K7 (statistical misspecification); K8 (non-stationarity of the relationship); K9 (baseline drift or expiry); K10 (indicator not meaningful as defined); K11 (multi-product allocation) | L44: destacada | N44: normalisation to a reference product | O44: proposed | P44: implicit | Q44: K11 | U44: normalisation to a reference product | V44: proposed | W44: implicit | X44: K11
A45: ADP-044 | B45: T1 | C45: rayyan-472535797 | D45: Ottermann (2011) | E45: 4 | G45: D1 → A1 | H45: In order to improve the monitoring and reporting of electrical energy consumption PPC is implementing the key performance indicators for each production step in the process for the electrical energy consumption in a cement plant: | I45: direct statement | K45: K1 (indicator not meaningful as defined) | L45: destacada | N45: improved metering | O45: implemented | P45: implicit | Q45: K1 | U45: improved metering | V45: implemented | W45: implicit | X45: K1
A46: ADP-046 | B46: T3 | C46: rayyan-472536226 | D46: El-Maghraby (2024) | E46: 3 | G46: D2 → A1 | H46: data sets were cleaned and validated by excluding abnormal values that were outside the Safe Operating Envelope (SOE). | I46: direct statement | K46: K1 (validity envelope exceeded) | L46: destacada | N46: outlier exclusion | O46: implemented | P46: absent | Q46: K1 | U46: outlier exclusion | V46: implemented | W46: absent | X46: K1
A47: ADP-045 | B47: T1 | C47: rayyan-472536226 | D47: El-Maghraby (2024) | E47: 5 | G47: D1 → M6 | H47: Specific Energy Consumption (SEC) was used in this work to compare the energy performance of different plants with the same boundaries. | I47: direct statement | K47: K1 (validity envelope exceeded) | L47: destacada | N47: normalisation to a reference product | O47: implemented | P47: ISO 50001/50006 explicit | U47: normalisation to a reference product | V47: implemented | W47: ISO 50001/50006 explicit
A48: ADP-047 | B48: T3 | C48: rayyan-472536358 | D48: Bassetti (2025) | E48: 13 | G48: D1 → M3 | H48: Hence, additional analysis by production intervals should be carried out. | I48: direct statement | K48: K1 (validity envelope exceeded); K2 (statistical misspecification); K3 (cross-site comparability); K4 (cross-site comparability); K5 (other) | L48: destacada | N48: segmented baseline | O48: proposed | P48: absent | U48: segmented baseline | V48: proposed | W48: absent
A49: ADP-049 | B49: T3 | C49: rayyan-472536358 | D49: Bassetti (2025) | E49: 13 | G49: D3 → M3 | H49: Finally, a detailed analysis of the distribution of share of final products (oxygen, nitrogen and argon) and its state (gas or liquid) is required to better understand the energy performance of the technical gas sector | I49: requires inference | K49: K1 (validity envelope exceeded); K2 (statistical misspecification); K3 (cross-site comparability); K4 (cross-site comparability); K5 (other) | L49: destacada | N49: normalisation to a reference product | O49: proposed | P49: absent | Q49: K3 | U49: normalisation to a reference product | V49: proposed | W49: absent | X49: K3
A50: ADP-048 | B50: T3 | C50: rayyan-472536358 | D50: Bassetti (2025) | E50: 15 | G50: D2 → M3 | H50: Further analysis will be focused on the analysis of different variables that affect energy efficiency of the industrial gases sector. | I50: direct statement | K50: K1 (validity envelope exceeded); K2 (statistical misspecification); K3 (cross-site comparability); K4 (cross-site comparability); K5 (other) | L50: destacada | N50: additional normalisation variable | O50: proposed | P50: absent | U50: additional normalisation variable | V50: proposed | W50: absent
A51: ADP-050 | B51: T1 | C51: rayyan-472536379 | D51: Khalid (2024) | E51: 5 | G51: D1 → M2 | H51: A new EnPI, using pretty much the same input parameters, but including information on the process, can thus be the answer. | I51: direct statement | K51: K1 (observability gap — quantity not measured); K2 (other) | L51: destacada | N51: additional normalisation variable | O51: evaluated | P51: implicit | Q51: K2 | U51: additional normalisation variable | V51: evaluated | W51: implicit | X51: K2
A52: ADP-051 | B52: T1 | C52: rayyan-472536379 | D52: Khalid (2024) | E52: 6 | G52: D2 → M1 | H52: selecting more locationspecific data, with higher temporal granularity (a week, a month, every change in the batch process, ...) and a more dedicated data gathering on the production itself (sub-process level) | I52: requires inference | K52: K1 (observability gap — quantity not measured); K2 (other) | L52: destacada | N52: improved metering | O52: proposed | P52: absent | Q52: K2 | U52: improved metering | V52: proposed | W52: absent | X52: K2
A53: ADP-052 | B53: T3 | C53: rayyan-472536410 | D53: Le-Anh (2023) | E53: 6 | G53: D1 → A1 | H53: The variation due to different pulp properties could be normalized by converting it into one main pulp. | I53: direct statement | K53: K1 (multi-product allocation); K2 (cross-site comparability); K3 (multi-product allocation); K4 (insufficient data length for the model) | L53: destacada | N53: normalisation to a reference product | O53: implemented | P53: absent | Q53: K1 | U53: normalisation to a reference product | V53: implemented | W53: absent | X53: K1
A54: ADP-053 | B54: T3 | C54: rayyan-472536410 | D54: Le-Anh (2023) | E54: 7 | G54: D2 → A1 | H54: it was finalized to carry out benchmarking per range of production scale for each sub-sector (i.e. packaging, tissue, writing and printing sub-sector). | I54: direct statement | K54: K1 (multi-product allocation); K2 (cross-site comparability); K3 (multi-product allocation); K4 (insufficient data length for the model) | L54: destacada | N54: segmented baseline | O54: implemented | P54: absent | U54: segmented baseline | V54: implemented | W54: absent
A55: ADP-054 | B55: T3 | C55: rayyan-472536428 | D55: Çaǧman (2022) | E55: 6 | G55: D1 → A1 | H55: New SES, SCAS, and SLS energy performance indicator parameters were presented to the literature in this study. | I55: direct statement | J55: adaptation other: New specific-saving energy performance indicators normalised to production: SES, SCAS and SLS | K55: K1 (non-stationarity of the relationship); K2 (observability gap — quantity not measured) | L55: destacada | N55: other | O55: proposed | P55: implicit | U55: other | V55: proposed | W55: implicit
A56: ADP-055 | B56: T3 | C56: rayyan-472536455 | D56: Bruni (2021) | E56: 8 | G56: D1 → A1 | H56: sites that are clearly far from the mean trend of the energy consumption vs. production ratio (outliers). | I56: direct statement | K56: K1 (cross-site comparability); K2 (indicator not meaningful as defined); K3 (statistical misspecification); K4 (statistical misspecification); K5 (statistical misspecification); K6 (non-stationarity of the relationship); K7 (data quality — missing, erroneous or discontinuous data) | L56: destacada | N56: outlier exclusion | O56: implemented | P56: absent | U56: outlier exclusion | V56: implemented | W56: absent
A57: ADP-059 | B57: T3 | C57: rayyan-472536455 | D57: Bruni (2021) | E57: 11 | G57: D5 → A1 | H57: This model can be used as the basis for more advanced models, such as stochastic frontier analysis (SFA) [31], index decomposition analysis (IDA) [50], or data envelopment analysis (DEA) [51] for calculation of energy-efﬁciency impact or deviation from benchmark. | I57: direct statement | J57: adaptation other: use of the EnPI model as basis for more advanced models (SFA, IDA, DEA) | K57: K1 (cross-site comparability); K2 (indicator not meaningful as defined); K3 (statistical misspecification); K4 (statistical misspecification); K5 (statistical misspecification); K6 (non-stationarity of the relationship); K7 (data quality — missing, erroneous or discontinuous data) | L57: destacada | N57: other | O57: proposed | P57: absent | U57: other | V57: proposed | W57: absent
A58: ADP-056 | B58: T3 | C58: rayyan-472536455 | D58: Bruni (2021) | E58: 14 | G58: D2 → A1 | H58: The normalization work that was pre-emptively accomplished in order to correct or dismiss nonhomogeneous elements: a partition of NACE group 23.51 depending on the characteristic processes of the sites. | I58: direct statement | K58: K1 (cross-site comparability); K2 (indicator not meaningful as defined); K3 (statistical misspecification); K4 (statistical misspecification); K5 (statistical misspecification); K6 (non-stationarity of the relationship); K7 (data quality — missing, erroneous or discontinuous data) | L58: destacada | N58: segmented baseline | O58: implemented | P58: absent | U58: segmented baseline | V58: implemented | W58: absent
A59: ADP-057 | B59: T3 | C59: rayyan-472536455 | D59: Bruni (2021) | E59: 16 | G59: D3 → A1 | H59: a “virtual” electric consumption related to the complete production cycle of all cement actually produced on the site was calculated. | I59: direct statement | K59: K1 (cross-site comparability); K2 (indicator not meaningful as defined); K3 (statistical misspecification); K4 (statistical misspecification); K5 (statistical misspecification); K6 (non-stationarity of the relationship); K7 (data quality — missing, erroneous or discontinuous data) | L59: destacada | N59: normalisation to a reference product | O59: implemented | P59: absent | U59: normalisation to a reference product | V59: implemented | W59: absent
A60: ADP-058 | B60: T1 | C60: rayyan-472536455 | D60: Bruni (2021) | E60: 22 | G60: D4 → M11 | H60: the impact of the number of cyclones on the pre-heating phase before clinker production was evaluated. | I60: direct statement | K60: K1 (cross-site comparability); K2 (indicator not meaningful as defined); K3 (statistical misspecification); K4 (statistical misspecification); K5 (statistical misspecification); K6 (non-stationarity of the relationship); K7 (data quality — missing, erroneous or discontinuous data) | L60: destacada | N60: additional normalisation variable | O60: evaluated | P60: absent | U60: additional normalisation variable | V60: evaluated | W60: absent
A61: ADP-060 | B61: T1 | C61: rayyan-472536486 | D61: Scripcariu (2021) | E61: 4 | G61: D1 → M2 | H61: If determined by using a weighted average price, the EI dropped by 4% to a weighted value of 0.38 t.o.e. per thousand EUR. | I61: direct statement | J61: adaptation other: recomputing Energy Intensity using a weighted average production price to remove the distortion caused by product price changes | K61: K1 (indicator not meaningful as defined); K2 (indicator not meaningful as defined); K3 (non-stationarity of the relationship) | L61: destacada | N61: other | O61: evaluated | P61: absent | Q61: K1 | U61: other | V61: evaluated | W61: absent | X61: K1
A62: ADP-061 | B62: T3 | C62: rayyan-472536487 | D62: Luknongbu (2021) | E62: 4 | G62: D1 → A1 | H62: The data from this factory excluded from the analysis. | I62: direct statement | K62: K1 (baseline drift or expiry); K2 (cross-site comparability) | L62: destacada | N62: outlier exclusion | O62: implemented | P62: absent | Q62: K2 | U62: outlier exclusion | V62: implemented | W62: absent | X62: K2
A63: ADP-062 | B63: T3 | C63: rayyan-472536487 | D63: Luknongbu (2021) | E63: 6 | G63: D2 → A1 | H63: However, the amount of energy consumption tends to change over times. BEC and SEC baseline should also be adjusted accordingly. | I63: direct statement | J63: adaptation other: periodic adjustment of BEC and SEC baseline as energy consumption changes over time | K63: K1 (baseline drift or expiry); K2 (cross-site comparability) | L63: destacada | N63: other | O63: proposed | P63: absent | Q63: K1 | U63: other | V63: proposed | W63: absent | X63: K1
A64: ADP-063 | B64: T3 | C64: rayyan-472536501 | D64: Guo (2020) | E64: 9 | G64: D1 → paper-level argument | H64: To solve the problem, the SBM-DEA model are proposed, which set different preference weights for input and output, and the sorting results are more distinct (Lozano and Gutierrez, 2011). | I64: direct statement | J64: adaptation other: SBM-DEA model setting preference weights for inputs and outputs | K64: K1 (other); K2 (other) | L64: destacada | N64: weighted estimation | O64: proposed | P64: absent | Q64: K1 | U64: weighted estimation | V64: proposed | W64: absent | X64: K1
A65: ADP-064 | B65: T1 | C65: rayyan-472536518 | D65: Maggiore (2020) | E65: 10 | G65: D1 → M1 | H65: for the replicability analysis of the projects in different sectors or different companies, it could be useful to have the process baseline consumption for each energy carrier to scale it to the desired technology (e.g. toe/ton of product); | I65: direct statement | K65: K1 (cross-site comparability); K2 (data quality — missing, erroneous or discontinuous data) | L65: destacada | N65: normalisation to a reference product | O65: proposed | P65: absent | U65: normalisation to a reference product | V65: proposed | W65: absent
A66: ADP-065 | B66: T1 | C66: rayyan-472536532 | D66: Beisheim (2019) | E66: 10 | G66: D1 → A1 | H66: The ambient temperature should be initially included in every analysis in order to be in accordance with normative standards (c.f. ISO 50006:2017 [20]). | I66: direct statement | K66: K1 (validity envelope exceeded); K2 (validity envelope exceeded); K3 (data quality — missing, erroneous or discontinuous data); K4 (baseline drift or expiry); K5 (insufficient data length for the model); K6 (non-stationarity of the relationship); K7 (statistical misspecification) | L66: não localizada automaticamente | N66: additional normalisation variable | O66: implemented | P66: ISO 50001/50006 explicit | U66: additional normalisation variable | V66: implemented | W66: ISO 50001/50006 explicit
A67: ADP-066 | B67: T1 | C67: rayyan-472536532 | D67: Beisheim (2019) | E67: 11 | G67: D2 → A1 | H67: Outlier removal is performed by ﬁltering data by specifying upper and lower bounds which deﬁne the typical operational envelope. | I67: direct statement | K67: K1 (validity envelope exceeded); K2 (validity envelope exceeded); K3 (data quality — missing, erroneous or discontinuous data); K4 (baseline drift or expiry); K5 (insufficient data length for the model); K6 (non-stationarity of the relationship); K7 (statistical misspecification) | L67: não localizada automaticamente | N67: outlier exclusion | O67: implemented | P67: absent | U67: outlier exclusion | V67: implemented | W67: absent
A68: ADP-069 | B68: T1 | C68: rayyan-472536532 | D68: Beisheim (2019) | E68: 17 | G68: D5 → A1 | H68: In order to overcome the shortcomings of linear regression models, ALAMO selects a combination of simple basis functions that ﬁt the responses with an acceptable accuracy. | I68: direct statement | J68: adaptation other: nonlinear surrogate model composed of simple basis functions to overcome shortcomings of linear regression | K68: K1 (validity envelope exceeded); K2 (validity envelope exceeded); K3 (data quality — missing, erroneous or discontinuous data); K4 (baseline drift or expiry); K5 (insufficient data length for the model); K6 (non-stationarity of the relationship); K7 (statistical misspecification) | L68: destacada | N68: other | O68: implemented | P68: absent | Q68: K7 | U68: other | V68: implemented | W68: absent | X68: K7
A69: ADP-067 | B69: T1 | C69: rayyan-472536532 | D69: Beisheim (2019) | E69: 18 | G69: D3 → A1 | H69: the diﬀerent weights of the clusters are considered using a Weighted Least Square (WLS) formulation in the objective function rather than the ordinary least square error | I69: direct statement | K69: K1 (validity envelope exceeded); K2 (validity envelope exceeded); K3 (data quality — missing, erroneous or discontinuous data); K4 (baseline drift or expiry); K5 (insufficient data length for the model); K6 (non-stationarity of the relationship); K7 (statistical misspecification) | L69: não localizada automaticamente | N69: weighted estimation | O69: implemented | P69: absent | U69: weighted estimation | V69: implemented | W69: absent
A70: ADP-068 | B70: T1 | C70: rayyan-472536532 | D70: Beisheim (2019) | E70: 25 | G70: D4 → A1 | H70: the proposed method can be applied to redeﬁne the energy baseline of a process after retroﬁtting (c.f. ISO 50001:2018). | I70: direct statement | J70: adaptation other: redefine the energy baseline of a process after retrofitting / re-evaluate the BDP after a period of time | K70: K1 (validity envelope exceeded); K2 (validity envelope exceeded); K3 (data quality — missing, erroneous or discontinuous data); K4 (baseline drift or expiry); K5 (insufficient data length for the model); K6 (non-stationarity of the relationship); K7 (statistical misspecification) | L70: destacada | N70: other | O70: proposed | P70: ISO 50001/50006 explicit | Q70: K4 | U70: other | V70: proposed | W70: ISO 50001/50006 explicit | X70: K4
A71: ADP-070 | B71: T1 | C71: rayyan-472536551 | D71: Hashim (2019) | E71: 14 | G71: D1 → M1 | H71: In addition, dedicated computer programming models can be developed if applicable to minimise the subjectivity of the outcome and for document control purposes. | I71: direct statement | J71: adaptation other: development of dedicated computer programming models to minimise subjectivity of the self-assessment outcome and for document control | K71: K1 (other); K2 (other) | L71: destacada | N71: other | O71: proposed | P71: absent | Q71: K2 | U71: other | V71: proposed | W71: absent | X71: K2
A72: ADP-071 | B72: T3 | C72: rayyan-472536606 | D72: Boyd (2017) | E72: 6 | G72: D1 → M1 | H72: One approach to controlling for product mix is to segment the industry into cohorts based on product categories. | I72: direct statement | K72: K1 (statistical misspecification); K2 (observability gap — quantity not measured); K3 (statistical misspecification); K4 (cross-site comparability); K5 (indicator not meaningful as defined); K6 (data quality — missing, erroneous or discontinuous data); K7 (indicator not meaningful as defined); K8 (multi-product allocation) | L72: destacada | N72: segmented baseline | O72: implemented | P72: absent | Q72: K8 | U72: segmented baseline | V72: implemented | W72: absent | X72: K8
A73: ADP-072 | B73: T3 | C73: rayyan-472536606 | D73: Boyd (2017) | E73: 6 | G73: D2 → M1 | H73: these studies use a multivariate approach to normalization where multiple effects are simultaneously considered | I73: direct statement | K73: K1 (statistical misspecification); K2 (observability gap — quantity not measured); K3 (statistical misspecification); K4 (cross-site comparability); K5 (indicator not meaningful as defined); K6 (data quality — missing, erroneous or discontinuous data); K7 (indicator not meaningful as defined); K8 (multi-product allocation) | L73: destacada | N73: additional normalisation variable | O73: implemented | P73: implicit | Q73: K5 | U73: additional normalisation variable | V73: implemented | W73: implicit | X73: K5
A74: ADP-073 | B74: T3 | C74: rayyan-472536606 | D74: Boyd (2017) | E74: 12 | G74: D3 → M2 | H74: All the case studies consider the possibility that efficiency is skewed and test whether a stochastic frontier (SF) energy model is appropriate | I74: direct statement | J74: adaptation other: stochastic frontier model to represent skewed efficiency distribution | K74: K1 (statistical misspecification); K2 (observability gap — quantity not measured); K3 (statistical misspecification); K4 (cross-site comparability); K5 (indicator not meaningful as defined); K6 (data quality — missing, erroneous or discontinuous data); K7 (indicator not meaningful as defined); K8 (multi-product allocation) | L74: destacada | N74: other | O74: implemented | P74: absent | U74: other | V74: implemented | W74: absent
A75: ADP-074 | B75: T3 | C75: rayyan-472536606 | D75: Boyd (2017) | E75: 13 | G75: D4 → M1 | H75: Two of the log normal models exhibit heteroscedastic distributions with variance declining with respect to production volumes. | I75: direct statement | K75: K1 (statistical misspecification); K2 (observability gap — quantity not measured); K3 (statistical misspecification); K4 (cross-site comparability); K5 (indicator not meaningful as defined); K6 (data quality — missing, erroneous or discontinuous data); K7 (indicator not meaningful as defined); K8 (multi-product allocation) | L75: destacada | N75: weighted estimation | O75: implemented | P75: absent | U75: weighted estimation | V75: implemented | W75: absent
A76: ADP-075 | B76: T3 | C76: rayyan-472536606 | D76: Boyd (2017) | E76: 21 | G76: D5 → M1 | H76: The process of benchmarking and rebenchmarking a sector provides further insights into the improvement potential of the industry over time. | I76: direct statement | J76: adaptation other: periodic re-benchmarking / update of the baseline (benchmark) year | K76: K1 (statistical misspecification); K2 (observability gap — quantity not measured); K3 (statistical misspecification); K4 (cross-site comparability); K5 (indicator not meaningful as defined); K6 (data quality — missing, erroneous or discontinuous data); K7 (indicator not meaningful as defined); K8 (multi-product allocation) | L76: destacada | N76: other | O76: implemented | P76: absent | Q76: K1 | U76: other | V76: implemented | W76: absent | X76: K1
A77: ADP-076 | B77: T1 | C77: rayyan-472536612 | D77: Bonfà (2017) | E77: 7 | G77: D1 → A1 | H77: Greater availability of data from measurements; could be defined a minimum measurement system in order to measure the amount of energy used by all the compressor park including the cooling system’s pumps and the compressed air produced by all the compressors (Fig. 5). | I77: direct statement | K77: K1 (data quality — missing, erroneous or discontinuous data); K2 (cross-site comparability); K3 (validity envelope exceeded); K4 (statistical misspecification); K5 (statistical misspecification); K6 (indicator not meaningful as defined); K7 (data quality — missing, erroneous or discontinuous data); K8 (observability gap — quantity not measured) | L77: destacada | N77: improved metering | O77: proposed | P77: implicit | Q77: K8 | U77: improved metering | V77: proposed | W77: implicit | X77: K8
A78: ADP-077 | B78: T3 | C78: rayyan-472536612 | D78: Bonfà (2017) | E78: 7 | G78: D2 → A1 | H78: In the event that the system has multiple pressure levels it would be useful to develop a statistical analysis system that considers the effect of pressure and develop different benchmarks based on the pressure level. | I78: direct statement | K78: K1 (data quality — missing, erroneous or discontinuous data); K2 (cross-site comparability); K3 (validity envelope exceeded); K4 (statistical misspecification); K5 (statistical misspecification); K6 (indicator not meaningful as defined); K7 (data quality — missing, erroneous or discontinuous data); K8 (observability gap — quantity not measured) | L78: destacada | N78: segmented baseline | O78: proposed | P78: absent | U78: segmented baseline | V78: proposed | W78: absent
A79: ADP-078 | B79: T3 | C79: rayyan-472536612 | D79: Bonfà (2017) | E79: 7 | G79: D3 → A1 | H79: Some further information about the pressure of compressed air generated. | I79: requires inference | K79: K1 (data quality — missing, erroneous or discontinuous data); K2 (cross-site comparability); K3 (validity envelope exceeded); K4 (statistical misspecification); K5 (statistical misspecification); K6 (indicator not meaningful as defined); K7 (data quality — missing, erroneous or discontinuous data); K8 (observability gap — quantity not measured) | L79: destacada | N79: additional normalisation variable | O79: proposed | P79: absent | Q79: K3 | U79: additional normalisation variable | V79: proposed | W79: absent | X79: K3
A80: ADP-079 | B80: T3 | C80: rayyan-472536612 | D80: Bonfà (2017) | E80: 8 | G80: D4 → A1 | H80: Data coming from firms could be used for a preliminary clustering and later perform the analysis cluster by cluster. | I80: direct statement | J80: adaptation other: clustering of enterprises before performing analysis cluster by cluster | K80: K1 (data quality — missing, erroneous or discontinuous data); K2 (cross-site comparability); K3 (validity envelope exceeded); K4 (statistical misspecification); K5 (statistical misspecification); K6 (indicator not meaningful as defined); K7 (data quality — missing, erroneous or discontinuous data); K8 (observability gap — quantity not measured) | L80: destacada | N80: other | O80: proposed | P80: absent | Q80: K2 | U80: other | V80: proposed | W80: absent | X80: K2
A81: ADP-080 | B81: T3 | C81: rayyan-472536612 | D81: Bonfà (2017) | E81: 8 | G81: D5 → A1 | H81: The regression method using measured data can help firms to analyze their electric consumption and thanks to control charts and CUSUM they can have a real-time monitoring system. | I81: direct statement | J81: adaptation other: control charts and CUSUM for real-time monitoring of consumption | K81: K1 (data quality — missing, erroneous or discontinuous data); K2 (cross-site comparability); K3 (validity envelope exceeded); K4 (statistical misspecification); K5 (statistical misspecification); K6 (indicator not meaningful as defined); K7 (data quality — missing, erroneous or discontinuous data); K8 (observability gap — quantity not measured) | L81: destacada | N81: other | O81: proposed | P81: implicit | U81: other | V81: proposed | W81: implicit
A82: ADP-083 | B82: T3 | C82: rayyan-472536644 | D82: Boyd (2016) | E82: 3 | G82: D3 → M1 | H82: the ENERGY STAR EPI uses a multivariate approach to normalization where multiple effects are simultaneously considered. | I82: direct statement | K82: K1 (indicator not meaningful as defined); K2 (data quality — missing, erroneous or discontinuous data); K3 (data quality — missing, erroneous or discontinuous data); K4 (statistical misspecification); K5 (non-stationarity of the relationship) | L82: destacada | N82: additional normalisation variable | O82: implemented | P82: implicit | Q82: K1 | U82: additional normalisation variable | V82: implemented | W82: implicit | X82: K1
A83: ADP-081 | B83: T3 | C83: rayyan-472536644 | D83: Boyd (2016) | E83: 6 | G83: D1 → M1 | H83: imputations were made to estimate oxygen usage for plants with missing observations. | I83: direct statement | J83: adaptation other: imputation of missing oxygen and scrap data using plant-specific ratios | K83: K1 (indicator not meaningful as defined); K2 (data quality — missing, erroneous or discontinuous data); K3 (data quality — missing, erroneous or discontinuous data); K4 (statistical misspecification); K5 (non-stationarity of the relationship) | L83: destacada | N83: other | O83: implemented | P83: absent | Q83: K2 | U83: other | V83: implemented | W83: absent | X83: K2
A84: ADP-082 | B84: T3 | C84: rayyan-472536644 | D84: Boyd (2016) | E84: 11 | G84: D2 → M1 | H84: the 2009 dummy variable was included in the final regression to account for the extreme impact on energy use in the recession. | I84: direct statement | K84: K1 (indicator not meaningful as defined); K2 (data quality — missing, erroneous or discontinuous data); K3 (data quality — missing, erroneous or discontinuous data); K4 (statistical misspecification); K5 (non-stationarity of the relationship) | L84: destacada | N84: additional normalisation variable | O84: implemented | P84: absent | Q84: K5 | U84: additional normalisation variable | V84: implemented | W84: absent | X84: K5
A85: ADP-085 | B85: T1 | C85: rayyan-472536693 | D85: Sivill (2013) | E85: 9 | G85: D2 → M1 | H85: the interviewees expressed a wish for the further development of measurement technology, general guidelines and public demonstration of energy performance measurement. | I85: direct statement | K85: K1 (non-stationarity of the relationship); K2 (observability gap — quantity not measured); K3 (other); K4 (other); K5 (cross-site comparability); K6 (indicator not meaningful as defined); K7 (indicator not meaningful as defined) | L85: destacada | N85: improved metering | O85: proposed | P85: absent | U85: improved metering | V85: proposed | W85: absent
A86: ADP-084 | B86: T3 | C86: rayyan-472536693 | D86: Sivill (2013) | E86: 12 | G86: D1 → M1 | H86: ‘There is some need for modelling and simple simulation models to be used for process operation’. | I86: direct statement | J86: adaptation other: modelling and simple simulation models for process operation | K86: K1 (non-stationarity of the relationship); K2 (observability gap — quantity not measured); K3 (other); K4 (other); K5 (cross-site comparability); K6 (indicator not meaningful as defined); K7 (indicator not meaningful as defined) | L86: destacada | N86: other | O86: proposed | P86: absent | U86: other | V86: proposed | W86: absent
A87: ADP-087 | B87: T3 | C87: rayyan-472536694 | D87: Boyd (2013) | E87: 4 | G87: D2 → M1 | H87: EPA agreed to develop a new EPI based on new data and released it to the industry so further improvement could be achieved. | I87: direct statement | J87: adaptation other: periodic update / re-estimation of the EPI benchmark using more recent data | K87: K1 (statistical misspecification); K2 (statistical misspecification); K3 (baseline drift or expiry); K4 (data quality — missing, erroneous or discontinuous data); K5 (multi-product allocation); K6 (other) | L87: destacada | N87: other | O87: implemented | P87: absent | Q87: K3 | U87: other | V87: implemented | W87: absent | X87: K3
A88: ADP-089 | B88: T3 | C88: rayyan-472536694 | D88: Boyd (2013) | E88: 7 | G88: D4 → M1 | H88: The new model captures the joint effect of producing clinker and finish grinding cement. | I88: direct statement | K88: K1 (statistical misspecification); K2 (statistical misspecification); K3 (baseline drift or expiry); K4 (data quality — missing, erroneous or discontinuous data); K5 (multi-product allocation); K6 (other) | L88: destacada | N88: additional normalisation variable | O88: implemented | P88: absent | Q88: K5 | U88: additional normalisation variable | V88: implemented | W88: absent | X88: K5
A89: ADP-086 | B89: T3 | C89: rayyan-472536694 | D89: Boyd (2013) | E89: 8 | G89: D1 → M1 | H89: the squared residuals were regressed against the inverse of the average capacity without an intercept | I89: direct statement | J89: adaptation other: modelling the error variance as a function of average kiln capacity (heteroscedastic variance) | K89: K1 (statistical misspecification); K2 (statistical misspecification); K3 (baseline drift or expiry); K4 (data quality — missing, erroneous or discontinuous data); K5 (multi-product allocation); K6 (other) | L89: destacada | N89: other | O89: implemented | P89: absent | Q89: K2 | U89: other | V89: implemented | W89: absent | X89: K2
A90: ADP-088 | B90: T3 | C90: rayyan-472536694 | D90: Boyd (2013) | E90: 9 | G90: D3 → M1 | H90: we adjust the intercept term, β0 in Eq. (1) to reflect the 1997 estimates of the impact of specialty cement production. | I90: direct statement | K90: K1 (statistical misspecification); K2 (statistical misspecification); K3 (baseline drift or expiry); K4 (data quality — missing, erroneous or discontinuous data); K5 (multi-product allocation); K6 (other) | L90: destacada | N90: additional normalisation variable | O90: implemented | P90: absent | Q90: K6 | U90: additional normalisation variable | V90: implemented | W90: absent | X90: K6
A91: ADP-090 | B91: T1 | C91: rayyan-472536695 | D91: Velázquez (2013) | E91: 7 | G91: D1 → M1 | H91: In a ﬁrst step of processing phase, 120 outliers corresponding to the days where the plant had unusual operation were ﬁltered and deleted from the training sample. | I91: direct statement | K91: K1 (baseline drift or expiry) | L91: destacada | N91: outlier exclusion | O91: implemented | P91: absent | U91: outlier exclusion | V91: implemented | W91: absent
A92: ADP-091 | B92: T1 | C92: rayyan-472536695 | D92: Velázquez (2013) | E92: 7 | G92: D2 → M1 | H92: For operation improvements, which imply changes of controllable variables to improve energy performance, baseline would be adjusted to actual external inﬂuence conditions. | I92: direct statement | K92: K1 (baseline drift or expiry) | L92: destacada | N92: additional normalisation variable | O92: implemented | P92: implicit | Q92: K1 | U92: additional normalisation variable | V92: implemented | W92: implicit | X92: K1

Sheet MODELOS
A1: Nº | B1: Tier | C1: Artigo | D1: Autor (ano) | E1: Pág. | F1: Pág. corrigida? | G1: Modelo | H1: Campo | I1: Contexto | J1: Citação | K1: support_class | L1: Localização no PDF | M1: Citação sustenta? | N1: Valor | O1: Nota | P1: Verificado | Q1: orig_Valor
A2: MOD-001 | B2: T1 | C2: rayyan-472535351 | D2: Almanza (2025) | E2: 7 | G2: A1/M1 «the simulation model» | H2: C5 data_origin | I2: vetor: natural gas | J2: In the simulation model of the refinery’s cogeneration plant, the output data used to validate the model is the natural gas consumed by the set of seven boilers. | K2: requires inference | L2: destacada | N2: simulation | Q2: simulation
A3: MOD-002 | B3: T1 | C3: rayyan-472535351 | D3: Almanza (2025) | E3: 7 | G3: A1/M1 «the simulation model» | H3: C5 boundary | I3: vetor: natural gas | J3: In the simulation model of the refinery’s cogeneration plant, the output data used to validate the model is the natural gas consumed by the set of seven boilers. | K3: requires inference | L3: destacada | N3: exact | Q3: exact
A4: MOD-003 | B4: T1 | C4: rayyan-472535351 | D4: Almanza (2025) | E4: 7 | G4: A1/M1 «the simulation model» | H4: C8 OOS status | I4: design: not reported; métricas: correlation coefficient between real and simulated natural gas consumption=0.6408; median percentage difference (real vs simulated natural gas)=7.8% | J4: the correlation coefficient between real and simulated data is 0.6408, which is a strong correlation according to Cohen, cited by Lalinde et al. (2018). | K4: direct statement | L4: destacada | N4: reported | Q4: reported
A5: MOD-004 | B5: T1 | C5: rayyan-472535365 | D5: Moghadasi (2025) | E5: 10 | G5: A1/M1 «the Gradient Boosting Machines (GBM) algorithm / GBM predict» | H5: C5 data_origin | I5: vetor: steam | J5: The present study considered data collected between January 2020 and January 2021 from a gas refinery's Distributed Control System (DCS) plant at Iran's South Pars Gas Complex. | K5: requires inference | L5: destacada | N5: process historian tag | Q5: process historian tag
A6: MOD-005 | B6: T1 | C6: rayyan-472535365 | D6: Moghadasi (2025) | E6: 10 | G6: A1/M1 «the Gradient Boosting Machines (GBM) algorithm / GBM predict» | H6: C5 boundary | I6: vetor: steam | J6: The present study considered data collected between January 2020 and January 2021 from a gas refinery's Distributed Control System (DCS) plant at Iran's South Pars Gas Complex. | K6: requires inference | L6: destacada | N6: exact | Q6: exact
A7: MOD-006 | B7: T1 | C7: rayyan-472535365 | D7: Moghadasi (2025) | E7: 12 | G7: A1/M1 «the Gradient Boosting Machines (GBM) algorithm / GBM predict» | H7: C8 OOS status | I7: design: held-out split; métricas: R2 (validation set)=0.99; RMSE (validation set)=108.8; RMAE (validation set)=0.14 | J7: the GBM algorithm performed as a robust and high-accuracy model with R2 (validation set) = 0.99, RSME (validation set) = 108.8 kg.hr−1 and RMAE (validation set) = 0.14% at predicting the steam flow rate of the EDU. | K7: direct statement | L7: destacada | N7: reported | Q7: reported
A8: MOD-007 | B8: T4 | C8: rayyan-472535480 | D8: Andersson (2021) | E8: 4 | G8: A1/M1 «SEC for both electricity and heat ... for the entire mill» | H8: C7 statement | I8: bounds: the range of accepted values for the EnPIs monitored (the mill's 'normal state of operation'), defined individually for each mill and connected to a certain grade of pulp produced | J8: EnPIs for systems and flow level mainly serve to identify deviations from what is defined as a mill's normal state of operation, i.e. the range of accepted values for the EnPIs monitored. | K8: direct statement | L8: destacada | N8: stated qualitatively | Q8: stated qualitatively
A9: MOD-008 | B9: T4 | C9: rayyan-472535480 | D9: Andersson (2021) | E9: 6 | G9: A1/M2 «the steam demand per amount of black liquor dry solids» | H9: C7 statement | I9: bounds: dry content of weak black liquor ranging from 15% (normal) to 25% (theoretical); normal vs. best point of operation | J9: Normal operation refers to the most likely point of operation. Best operation refers to an optimal state of operation that is considered long enough to be steady-state. | K9: direct statement | L9: destacada | N9: stated qualitatively | Q9: stated qualitatively
A10: MOD-011 | B10: T1 | C10: rayyan-472535524 | D10: Beisheim (2020) | E10: 4 | G10: A1/M1 «the EnPI of the aggregated site» | H10: C5 data_origin | I10: vetor: steam | J10: These flows do not cross the system boundary and thus are not considered as products of the aggregated RMU. | K10: requires inference | L10: destacada | N10: calculated from process data | Q10: calculated from process data
A11: MOD-012 | B11: T1 | C11: rayyan-472535524 | D11: Beisheim (2020) | E11: 4 | G11: A1/M1 «the EnPI of the aggregated site» | H11: C5 boundary | I11: vetor: steam | J11: These flows do not cross the system boundary and thus are not considered as products of the aggregated RMU. | K11: requires inference | L11: destacada | N11: allocated by rule | Q11: allocated by rule
A12: MOD-009 | B12: T1 | C12: rayyan-472535524 | D12: Beisheim (2020) | E12: 7 | G12: A1/M1 «the EnPI of the aggregated site» | H12: C5 data_origin | I12: vetor: electricity | J12: The electric power and steam demands are covered by imports from the grid. | K12: requires inference | L12: destacada | N12: not reported | Q12: not reported
A13: MOD-010 | B13: T1 | C13: rayyan-472535524 | D13: Beisheim (2020) | E13: 7 | G13: A1/M1 «the EnPI of the aggregated site» | H13: C5 boundary | I13: vetor: electricity | J13: The electric power and steam demands are covered by imports from the grid. | K13: requires inference | L13: destacada | N13: exact | Q13: exact
... A133: MOD-132 | B133: T1 | C133: rayyan-472536695 | D133: Velázquez (2013) | E133: 7 | G133: A1/M1 «The regression model of SCPU» | H133: C5 boundary | I133: vetor: steam | J133: Many variables are measured and collected in the PU. | K133: requires inference | L133: destacada | N133: exact | Q133: exact

Sheet Tempos
A1: Artigo | B1: Autor (ano) | C1: Itens | D1: Itens T1 | E1: Minutos (preencher) | F1: Min/item
A2: rayyan-472535351 | B2: Almanza (2025) | C2: =COUNTIF(MEC!$C:$C,A2)+COUNTIF(ADP!$C:$C,A2)+COUNTIF(MODELOS!$C:$C,A2) -> 8 | D2: =COUNTIFS(MEC!$C:$C,A2,MEC!$B:$B,"T1")+COUNTIFS(ADP!$C:$C,A2,ADP!$B:$B,"T1")+COUNTIFS(MODELOS!$C:$C,A2,MODELOS!$B:$B,"T1") -> 8 | F2: =IF(E2="","",E2/C2)
A3: rayyan-472535365 | B3: Moghadasi (2025) | C3: =COUNTIF(MEC!$C:$C,A3)+COUNTIF(ADP!$C:$C,A3)+COUNTIF(MODELOS!$C:$C,A3) -> 8 | D3: =COUNTIFS(MEC!$C:$C,A3,MEC!$B:$B,"T1")+COUNTIFS(ADP!$C:$C,A3,ADP!$B:$B,"T1")+COUNTIFS(MODELOS!$C:$C,A3,MODELOS!$B:$B,"T1") -> 8 | F3: =IF(E3="","",E3/C3)
A4: rayyan-472535376 | B4: Benmakhlouf (2025) | C4: =COUNTIF(MEC!$C:$C,A4)+COUNTIF(ADP!$C:$C,A4)+COUNTIF(MODELOS!$C:$C,A4) -> 2 | D4: =COUNTIFS(MEC!$C:$C,A4,MEC!$B:$B,"T1")+COUNTIFS(ADP!$C:$C,A4,ADP!$B:$B,"T1")+COUNTIFS(MODELOS!$C:$C,A4,MODELOS!$B:$B,"T1") -> 0 | F4: =IF(E4="","",E4/C4)
A5: rayyan-472535405 | B5: Khalid (2024) | C5: =COUNTIF(MEC!$C:$C,A5)+COUNTIF(ADP!$C:$C,A5)+COUNTIF(MODELOS!$C:$C,A5) -> 4 | D5: =COUNTIFS(MEC!$C:$C,A5,MEC!$B:$B,"T1")+COUNTIFS(ADP!$C:$C,A5,ADP!$B:$B,"T1")+COUNTIFS(MODELOS!$C:$C,A5,MODELOS!$B:$B,"T1") -> 1 | F5: =IF(E5="","",E5/C5)
A6: rayyan-472535480 | B6: Andersson (2021) | C6: =COUNTIF(MEC!$C:$C,A6)+COUNTIF(ADP!$C:$C,A6)+COUNTIF(MODELOS!$C:$C,A6) -> 10 | D6: =COUNTIFS(MEC!$C:$C,A6,MEC!$B:$B,"T1")+COUNTIFS(ADP!$C:$C,A6,ADP!$B:$B,"T1")+COUNTIFS(MODELOS!$C:$C,A6,MODELOS!$B:$B,"T1") -> 4 | F6: =IF(E6="","",E6/C6)
A7: rayyan-472535522 | B7: Espinel-Blanco (2020) | C7: =COUNTIF(MEC!$C:$C,A7)+COUNTIF(ADP!$C:$C,A7)+COUNTIF(MODELOS!$C:$C,A7) -> 4 | D7: =COUNTIFS(MEC!$C:$C,A7,MEC!$B:$B,"T1")+COUNTIFS(ADP!$C:$C,A7,ADP!$B:$B,"T1")+COUNTIFS(MODELOS!$C:$C,A7,MODELOS!$B:$B,"T1") -> 1 | F7: =IF(E7="","",E7/C7)
A8: rayyan-472535524 | B8: Beisheim (2020) | C8: =COUNTIF(MEC!$C:$C,A8)+COUNTIF(ADP!$C:$C,A8)+COUNTIF(MODELOS!$C:$C,A8) -> 21 | D8: =COUNTIFS(MEC!$C:$C,A8,MEC!$B:$B,"T1")+COUNTIFS(ADP!$C:$C,A8,ADP!$B:$B,"T1")+COUNTIFS(MODELOS!$C:$C,A8,MODELOS!$B:$B,"T1") -> 21 | F8: =IF(E8="","",E8/C8)
A9: rayyan-472535532 | B9: Mahesthi (2020) | C9: =COUNTIF(MEC!$C:$C,A9)+COUNTIF(ADP!$C:$C,A9)+COUNTIF(MODELOS!$C:$C,A9) -> 11 | D9: =COUNTIFS(MEC!$C:$C,A9,MEC!$B:$B,"T1")+COUNTIFS(ADP!$C:$C,A9,ADP!$B:$B,"T1")+COUNTIFS(MODELOS!$C:$C,A9,MODELOS!$B:$B,"T1") -> 2 | F9: =IF(E9="","",E9/C9)
A10: rayyan-472535550 | B10: Hamedi (2019) | C10: =COUNTIF(MEC!$C:$C,A10)+COUNTIF(ADP!$C:$C,A10)+COUNTIF(MODELOS!$C:$C,A10) -> 21 | D10: =COUNTIFS(MEC!$C:$C,A10,MEC!$B:$B,"T1")+COUNTIFS(ADP!$C:$C,A10,ADP!$B:$B,"T1")+COUNTIFS(MODELOS!$C:$C,A10,MODELOS!$B:$B,"T1") -> 21 | F10: =IF(E10="","",E10/C10)
A11: rayyan-472535582 | B11: Morales (2018) | C11: =COUNTIF(MEC!$C:$C,A11)+COUNTIF(ADP!$C:$C,A11)+COUNTIF(MODELOS!$C:$C,A11) -> 22 | D11: =COUNTIFS(MEC!$C:$C,A11,MEC!$B:$B,"T1")+COUNTIFS(ADP!$C:$C,A11,ADP!$B:$B,"T1")+COUNTIFS(MODELOS!$C:$C,A11,MODELOS!$B:$B,"T1") -> 22 | F11: =IF(E11="","",E11/C11)
A12: rayyan-472535585 | B12: Pelser (2018) | C12: =COUNTIF(MEC!$C:$C,A12)+COUNTIF(ADP!$C:$C,A12)+COUNTIF(MODELOS!$C:$C,A12) -> 12 | D12: =COUNTIFS(MEC!$C:$C,A12,MEC!$B:$B,"T1")+COUNTIFS(ADP!$C:$C,A12,ADP!$B:$B,"T1")+COUNTIFS(MODELOS!$C:$C,A12,MODELOS!$B:$B,"T1") -> 3 | F12: =IF(E12="","",E12/C12)
A13: rayyan-472535625 | B13: Ikeyama (2017) | C13: =COUNTIF(MEC!$C:$C,A13)+COUNTIF(ADP!$C:$C,A13)+COUNTIF(MODELOS!$C:$C,A13) -> 7 | D13: =COUNTIFS(MEC!$C:$C,A13,MEC!$B:$B,"T1")+COUNTIFS(ADP!$C:$C,A13,ADP!$B:$B,"T1")+COUNTIFS(MODELOS!$C:$C,A13,MODELOS!$B:$B,"T1") -> 7 | F13: =IF(E13="","",E13/C13)
... A39: rayyan-472536695 | B39: Velázquez (2013) | C39: =COUNTIF(MEC!$C:$C,A39)+COUNTIF(ADP!$C:$C,A39)+COUNTIF(MODELOS!$C:$C,A39) -> 7 | D39: =COUNTIFS(MEC!$C:$C,A39,MEC!$B:$B,"T1")+COUNTIFS(ADP!$C:$C,A39,ADP!$B:$B,"T1")+COUNTIFS(MODELOS!$C:$C,A39,MODELOS!$B:$B,"T1") -> 7 | F39: =IF(E39="","",E39/C39)
